[
    {
        "doc_id": "194291859",
        "date": "2014.03.28."
    },
    {
        "doc_id": "194346650",
        "date": "2014.03.28."
    },
    {
        "doc_id": "194350179",
        "date": "2014.03.28."
    },
    {
        "doc_id": "194350723",
        "date": "2014.03.28."
    },
    {
        "doc_id": "194228524",
        "date": "2014.03.26."
    },
    {
        "doc_id": "194058327",
        "date": "2014.03.25."
    },
    {
        "doc_id": "194052048",
        "date": "2014.03.25."
    },
    {
        "doc_id": "194081133",
        "date": "2014.03.25."
    },
    {
        "doc_id": "194123923",
        "date": "2014.03.25."
    },
    {
        "doc_id": "194135525",
        "date": "2014.03.25."
    },
    {
        "doc_id": "194162949",
        "date": "2014.03.25."
    },
    {
        "doc_id": "193328793",
        "date": "2014.03.13."
    },
    {
        "doc_id": "193263263",
        "date": "2014.03.12."
    },
    {
        "doc_id": "193183148",
        "date": "2014.03.12."
    },
    {
        "doc_id": "193191471",
        "date": "2014.03.12."
    },
    {
        "doc_id": "193197623",
        "date": "2014.03.12."
    },
    {
        "doc_id": "192350562",
        "date": "2014.02.28."
    },
    {
        "doc_id": "192203554",
        "date": "2014.02.28."
    },
    {
        "doc_id": "191987124",
        "date": "2014.02.27."
    },
    {
        "doc_id": "192004196",
        "date": "2014.02.24."
    },
    {
        "doc_id": "192007019",
        "date": "2014.02.24."
    },
    {
        "doc_id": "191236587",
        "date": "2014.02.17."
    },
    {
        "doc_id": "191269389",
        "date": "2014.02.17."
    },
    {
        "doc_id": "191300569",
        "date": "2014.02.17."
    },
    {
        "doc_id": "191286930",
        "date": "2014.02.17."
    },
    {
        "doc_id": "191295537",
        "date": "2014.02.17."
    },
    {
        "doc_id": "191381004",
        "date": "2014.02.17."
    },
    {
        "doc_id": "191294211",
        "date": "2014.02.17."
    },
    {
        "doc_id": "190912506",
        "date": "2014.02.11."
    },
    {
        "doc_id": "190812789",
        "date": "2014.02.11."
    },
    {
        "doc_id": "190751936",
        "date": "2014.02.11."
    },
    {
        "doc_id": "190740828",
        "date": "2014.02.11."
    },
    {
        "doc_id": "190691489",
        "date": "2014.02.11."
    },
    {
        "doc_id": "189930187",
        "date": "2014.01.29."
    },
    {
        "doc_id": "189933294",
        "date": "2014.01.29."
    },
    {
        "doc_id": "189774268",
        "date": "2014.01.28."
    },
    {
        "doc_id": "189791556",
        "date": "2014.01.28."
    },
    {
        "doc_id": "189793122",
        "date": "2014.01.28."
    },
    {
        "doc_id": "189824350",
        "date": "2014.01.28."
    },
    {
        "doc_id": "189833348",
        "date": "2014.01.28."
    },
    {
        "doc_id": "189831477",
        "date": "2014.01.28."
    },
    {
        "doc_id": "189837277",
        "date": "2014.01.28."
    },
    {
        "doc_id": "189659053",
        "date": "2014.01.27."
    },
    {
        "doc_id": "189135848",
        "date": "2014.01.20."
    },
    {
        "doc_id": "189007289",
        "date": "2014.01.20."
    },
    {
        "doc_id": "188797788",
        "date": "2014.01.16."
    },
    {
        "doc_id": "188821865",
        "date": "2014.01.16."
    },
    {
        "doc_id": "188831993",
        "date": "2014.01.16."
    },
    {
        "doc_id": "188401527",
        "date": "2014.01.14."
    },
    {
        "doc_id": "188601786",
        "date": "2014.01.14."
    },
    {
        "doc_id": "188626945",
        "date": "2014.01.14."
    },
    {
        "doc_id": "188644483",
        "date": "2014.01.14."
    },
    {
        "doc_id": "187688331",
        "date": "2014.01.02."
    },
    {
        "doc_id": "187556529",
        "date": "2014.01.02."
    },
    {
        "doc_id": "187525885",
        "date": "2014.01.02."
    },
    {
        "doc_id": "187433090",
        "date": "2013.12.31."
    },
    {
        "doc_id": "187407631",
        "date": "2013.12.31."
    },
    {
        "doc_id": "187432962",
        "date": "2013.12.31."
    },
    {
        "doc_id": "187191669",
        "date": "2013.12.30."
    },
    {
        "doc_id": "187012068",
        "date": "2013.12.22."
    },
    {
        "doc_id": "187001743",
        "date": "2013.12.22."
    },
    {
        "doc_id": "187031835",
        "date": "2013.12.22."
    },
    {
        "doc_id": "187007849",
        "date": "2013.12.22."
    },
    {
        "doc_id": "187020927",
        "date": "2013.12.22."
    },
    {
        "doc_id": "187020983",
        "date": "2013.12.22."
    },
    {
        "doc_id": "187024491",
        "date": "2013.12.22."
    },
    {
        "doc_id": "186495472",
        "date": "2013.12.19."
    },
    {
        "doc_id": "186757166",
        "date": "2013.12.18."
    },
    {
        "doc_id": "186705946",
        "date": "2013.12.17."
    },
    {
        "doc_id": "186709945",
        "date": "2013.12.17."
    },
    {
        "doc_id": "186698665",
        "date": "2013.12.17."
    },
    {
        "doc_id": "186695612",
        "date": "2013.12.17."
    },
    {
        "doc_id": "186694291",
        "date": "2013.12.17."
    },
    {
        "doc_id": "186330857",
        "date": "2013.12.11."
    },
    {
        "doc_id": "186054996",
        "date": "2013.12.08."
    },
    {
        "doc_id": "186015055",
        "date": "2013.12.07."
    },
    {
        "doc_id": "186021228",
        "date": "2013.12.07."
    },
    {
        "doc_id": "185938538",
        "date": "2013.12.06."
    },
    {
        "doc_id": "185931883",
        "date": "2013.12.06."
    },
    {
        "doc_id": "185937579",
        "date": "2013.12.06."
    },
    {
        "doc_id": "185944070",
        "date": "2013.12.06."
    },
    {
        "doc_id": "185876229",
        "date": "2013.12.05."
    },
    {
        "doc_id": "185878921",
        "date": "2013.12.05."
    },
    {
        "doc_id": "185876095",
        "date": "2013.12.05."
    },
    {
        "doc_id": "185837510",
        "date": "2013.12.05."
    },
    {
        "doc_id": "185464325",
        "date": "2013.12.03."
    },
    {
        "doc_id": "185171457",
        "date": "2013.11.25."
    },
    {
        "doc_id": "185205714",
        "date": "2013.11.25."
    },
    {
        "doc_id": "185203404",
        "date": "2013.11.25."
    },
    {
        "doc_id": "185206024",
        "date": "2013.11.25."
    },
    {
        "doc_id": "185199114",
        "date": "2013.11.25."
    },
    {
        "doc_id": "185207174",
        "date": "2013.11.25."
    },
    {
        "doc_id": "185214137",
        "date": "2013.11.25."
    },
    {
        "doc_id": "185150147",
        "date": "2013.11.24."
    },
    {
        "doc_id": "185141531",
        "date": "2013.11.24."
    },
    {
        "doc_id": "185159218",
        "date": "2013.11.24."
    },
    {
        "doc_id": "184839027",
        "date": "2013.11.19."
    },
    {
        "doc_id": "184847033",
        "date": "2013.11.19."
    },
    {
        "doc_id": "184340870",
        "date": "2013.11.11."
    },
    {
        "doc_id": "184157891",
        "date": "2013.11.08."
    },
    {
        "doc_id": "184137481",
        "date": "2013.11.08."
    },
    {
        "doc_id": "184145296",
        "date": "2013.11.08."
    },
    {
        "doc_id": "184078235",
        "date": "2013.11.07."
    },
    {
        "doc_id": "184079710",
        "date": "2013.11.07."
    },
    {
        "doc_id": "183946330",
        "date": "2013.11.06."
    },
    {
        "doc_id": "183982338",
        "date": "2013.11.05."
    },
    {
        "doc_id": "183887253",
        "date": "2013.11.05."
    },
    {
        "doc_id": "183893461",
        "date": "2013.11.05."
    },
    {
        "doc_id": "183436034",
        "date": "2013.10.28."
    },
    {
        "doc_id": "183337300",
        "date": "2013.10.28."
    },
    {
        "doc_id": "183359229",
        "date": "2013.10.28."
    },
    {
        "doc_id": "183413774",
        "date": "2013.10.28."
    },
    {
        "doc_id": "183422254",
        "date": "2013.10.28."
    },
    {
        "doc_id": "183299083",
        "date": "2013.10.26."
    },
    {
        "doc_id": "183248967",
        "date": "2013.10.26."
    },
    {
        "doc_id": "183262345",
        "date": "2013.10.26."
    },
    {
        "doc_id": "183261632",
        "date": "2013.10.26."
    },
    {
        "doc_id": "183290632",
        "date": "2013.10.26."
    },
    {
        "doc_id": "183241824",
        "date": "2013.10.25."
    },
    {
        "doc_id": "183231549",
        "date": "2013.10.25."
    },
    {
        "doc_id": "183176055",
        "date": "2013.10.24."
    },
    {
        "doc_id": "183165865",
        "date": "2013.10.24."
    },
    {
        "doc_id": "183121468",
        "date": "2013.10.23."
    },
    {
        "doc_id": "183118316",
        "date": "2013.10.23."
    }
]