[
    {
        "doc_id": "464235190",
        "date": "2024.02.14."
    },
    {
        "doc_id": "463737256",
        "date": "2024.02.06."
    },
    {
        "doc_id": "463263729",
        "date": "2024.01.30."
    },
    {
        "doc_id": "462287537",
        "date": "2024.01.16."
    },
    {
        "doc_id": "462363389",
        "date": "2024.01.16."
    },
    {
        "doc_id": "462317536",
        "date": "2024.01.16."
    },
    {
        "doc_id": "461850265",
        "date": "2024.01.09."
    },
    {
        "doc_id": "461414692",
        "date": "2024.01.02."
    },
    {
        "doc_id": "461081655",
        "date": "2023.12.27."
    },
    {
        "doc_id": "460630749",
        "date": "2023.12.19."
    },
    {
        "doc_id": "460208933",
        "date": "2023.12.12."
    },
    {
        "doc_id": "459779563",
        "date": "2023.12.05."
    },
    {
        "doc_id": "459352528",
        "date": "2023.11.28."
    },
    {
        "doc_id": "458937505",
        "date": "2023.11.21."
    },
    {
        "doc_id": "458510517",
        "date": "2023.11.14."
    },
    {
        "doc_id": "458069895",
        "date": "2023.11.07."
    },
    {
        "doc_id": "457173882",
        "date": "2023.10.24."
    },
    {
        "doc_id": "456724468",
        "date": "2023.10.17."
    },
    {
        "doc_id": "456251257",
        "date": "2023.10.10."
    },
    {
        "doc_id": "455378803",
        "date": "2023.09.26."
    },
    {
        "doc_id": "454926807",
        "date": "2023.09.19."
    },
    {
        "doc_id": "454443850",
        "date": "2023.09.12."
    },
    {
        "doc_id": "453964372",
        "date": "2023.09.05."
    },
    {
        "doc_id": "453460280",
        "date": "2023.08.29."
    },
    {
        "doc_id": "452948511",
        "date": "2023.08.22."
    },
    {
        "doc_id": "452498680",
        "date": "2023.08.16."
    },
    {
        "doc_id": "451892399",
        "date": "2023.08.08."
    },
    {
        "doc_id": "450858394",
        "date": "2023.07.25."
    },
    {
        "doc_id": "450360678",
        "date": "2023.07.18."
    },
    {
        "doc_id": "449876722",
        "date": "2023.07.11."
    },
    {
        "doc_id": "449395113",
        "date": "2023.07.04."
    },
    {
        "doc_id": "448904834",
        "date": "2023.06.27."
    },
    {
        "doc_id": "448479031",
        "date": "2023.06.21."
    },
    {
        "doc_id": "447904122",
        "date": "2023.06.13."
    },
    {
        "doc_id": "447459434",
        "date": "2023.06.07."
    },
    {
        "doc_id": "446976169",
        "date": "2023.05.31."
    },
    {
        "doc_id": "446427222",
        "date": "2023.05.23."
    },
    {
        "doc_id": "445930655",
        "date": "2023.05.16."
    },
    {
        "doc_id": "445456682",
        "date": "2023.05.09."
    },
    {
        "doc_id": "445042089",
        "date": "2023.05.03."
    },
    {
        "doc_id": "444507428",
        "date": "2023.04.25."
    },
    {
        "doc_id": "444017430",
        "date": "2023.04.18."
    },
    {
        "doc_id": "443529396",
        "date": "2023.04.11."
    },
    {
        "doc_id": "443022620",
        "date": "2023.04.04."
    },
    {
        "doc_id": "442553994",
        "date": "2023.03.28."
    },
    {
        "doc_id": "442066879",
        "date": "2023.03.21."
    },
    {
        "doc_id": "441623248",
        "date": "2023.03.14."
    },
    {
        "doc_id": "441572157",
        "date": "2023.03.14."
    },
    {
        "doc_id": "441076835",
        "date": "2023.03.07."
    },
    {
        "doc_id": "439981374",
        "date": "2023.02.21."
    },
    {
        "doc_id": "438834282",
        "date": "2023.02.07."
    },
    {
        "doc_id": "438250709",
        "date": "2023.01.31."
    },
    {
        "doc_id": "437155531",
        "date": "2023.01.17."
    },
    {
        "doc_id": "436605492",
        "date": "2023.01.10."
    },
    {
        "doc_id": "436089167",
        "date": "2023.01.03."
    },
    {
        "doc_id": "435610847",
        "date": "2022.12.27."
    },
    {
        "doc_id": "435142294",
        "date": "2022.12.20."
    },
    {
        "doc_id": "434653718",
        "date": "2022.12.13."
    },
    {
        "doc_id": "434166820",
        "date": "2022.12.06."
    },
    {
        "doc_id": "433755856",
        "date": "2022.11.29."
    },
    {
        "doc_id": "433756519",
        "date": "2022.11.29."
    },
    {
        "doc_id": "433702719",
        "date": "2022.11.29."
    },
    {
        "doc_id": "433215617",
        "date": "2022.11.22."
    },
    {
        "doc_id": "432698840",
        "date": "2022.11.15."
    },
    {
        "doc_id": "432201417",
        "date": "2022.11.08."
    },
    {
        "doc_id": "431706201",
        "date": "2022.11.01."
    },
    {
        "doc_id": "430726965",
        "date": "2022.10.18."
    },
    {
        "doc_id": "430286231",
        "date": "2022.10.12."
    },
    {
        "doc_id": "429840789",
        "date": "2022.10.05."
    },
    {
        "doc_id": "429840134",
        "date": "2022.10.05."
    },
    {
        "doc_id": "429784237",
        "date": "2022.10.05."
    },
    {
        "doc_id": "429201373",
        "date": "2022.09.27."
    },
    {
        "doc_id": "428709893",
        "date": "2022.09.20."
    },
    {
        "doc_id": "428251319",
        "date": "2022.09.14."
    },
    {
        "doc_id": "427696130",
        "date": "2022.09.06."
    },
    {
        "doc_id": "427205009",
        "date": "2022.08.30."
    },
    {
        "doc_id": "426706949",
        "date": "2022.08.23."
    },
    {
        "doc_id": "425787053",
        "date": "2022.08.10."
    },
    {
        "doc_id": "425705846",
        "date": "2022.08.10."
    },
    {
        "doc_id": "425119322",
        "date": "2022.08.02."
    },
    {
        "doc_id": "424603599",
        "date": "2022.07.26."
    },
    {
        "doc_id": "424618577",
        "date": "2022.07.26."
    },
    {
        "doc_id": "424619979",
        "date": "2022.07.26."
    },
    {
        "doc_id": "424615484",
        "date": "2022.07.26."
    },
    {
        "doc_id": "424117517",
        "date": "2022.07.19."
    },
    {
        "doc_id": "423660329",
        "date": "2022.07.12."
    },
    {
        "doc_id": "423176852",
        "date": "2022.07.05."
    },
    {
        "doc_id": "422677598",
        "date": "2022.06.28."
    },
    {
        "doc_id": "422188628",
        "date": "2022.06.21."
    },
    {
        "doc_id": "421679430",
        "date": "2022.06.14."
    },
    {
        "doc_id": "421228111",
        "date": "2022.06.08."
    },
    {
        "doc_id": "420651276",
        "date": "2022.05.31."
    },
    {
        "doc_id": "420142813",
        "date": "2022.05.24."
    },
    {
        "doc_id": "419184163",
        "date": "2022.05.11."
    },
    {
        "doc_id": "418596925",
        "date": "2022.05.03."
    },
    {
        "doc_id": "418088950",
        "date": "2022.04.26."
    },
    {
        "doc_id": "417600137",
        "date": "2022.04.19."
    },
    {
        "doc_id": "417554334",
        "date": "2022.04.19."
    },
    {
        "doc_id": "416991021",
        "date": "2022.04.13."
    },
    {
        "doc_id": "417067991",
        "date": "2022.04.13."
    },
    {
        "doc_id": "417068296",
        "date": "2022.04.13."
    },
    {
        "doc_id": "417011409",
        "date": "2022.04.12."
    },
    {
        "doc_id": "416461937",
        "date": "2022.04.05."
    },
    {
        "doc_id": "415918150",
        "date": "2022.03.29."
    },
    {
        "doc_id": "415348245",
        "date": "2022.03.22."
    },
    {
        "doc_id": "414749404",
        "date": "2022.03.16."
    },
    {
        "doc_id": "414768194",
        "date": "2022.03.15."
    },
    {
        "doc_id": "413769005",
        "date": "2022.03.03."
    },
    {
        "doc_id": "412950339",
        "date": "2022.02.22."
    },
    {
        "doc_id": "412288416",
        "date": "2022.02.15."
    },
    {
        "doc_id": "410291917",
        "date": "2022.01.23."
    },
    {
        "doc_id": "409977100",
        "date": "2022.01.19."
    },
    {
        "doc_id": "409979642",
        "date": "2022.01.18."
    },
    {
        "doc_id": "409898307",
        "date": "2022.01.18."
    },
    {
        "doc_id": "409324750",
        "date": "2022.01.11."
    },
    {
        "doc_id": "408768357",
        "date": "2022.01.04."
    },
    {
        "doc_id": "408769710",
        "date": "2022.01.04."
    },
    {
        "doc_id": "408250978",
        "date": "2021.12.28."
    },
    {
        "doc_id": "407264142",
        "date": "2021.12.15."
    },
    {
        "doc_id": "407290396",
        "date": "2021.12.15."
    },
    {
        "doc_id": "406322451",
        "date": "2021.12.02."
    },
    {
        "doc_id": "406169259",
        "date": "2021.12.02."
    },
    {
        "doc_id": "405668956",
        "date": "2021.11.24."
    },
    {
        "doc_id": "405141819",
        "date": "2021.11.17."
    },
    {
        "doc_id": "404534095",
        "date": "2021.11.08."
    },
    {
        "doc_id": "404473295",
        "date": "2021.11.08."
    },
    {
        "doc_id": "404533477",
        "date": "2021.11.08."
    },
    {
        "doc_id": "404387375",
        "date": "2021.11.08."
    },
    {
        "doc_id": "404400950",
        "date": "2021.11.08."
    },
    {
        "doc_id": "404316127",
        "date": "2021.11.08."
    },
    {
        "doc_id": "404084357",
        "date": "2021.11.03."
    },
    {
        "doc_id": "402493816",
        "date": "2021.10.15."
    },
    {
        "doc_id": "401851886",
        "date": "2021.10.07."
    },
    {
        "doc_id": "401198424",
        "date": "2021.09.30."
    },
    {
        "doc_id": "401285090",
        "date": "2021.09.30."
    },
    {
        "doc_id": "399964218",
        "date": "2021.09.15."
    },
    {
        "doc_id": "398971237",
        "date": "2021.09.04."
    },
    {
        "doc_id": "399069259",
        "date": "2021.09.04."
    },
    {
        "doc_id": "371770372",
        "date": "2020.10.27."
    },
    {
        "doc_id": "346521829",
        "date": "2020.02.06."
    },
    {
        "doc_id": "346439159",
        "date": "2020.02.06."
    },
    {
        "doc_id": "346439616",
        "date": "2020.02.06."
    },
    {
        "doc_id": "346347886",
        "date": "2020.02.06."
    },
    {
        "doc_id": "346443829",
        "date": "2020.02.05."
    },
    {
        "doc_id": "346349084",
        "date": "2020.02.05."
    },
    {
        "doc_id": "346444266",
        "date": "2020.02.05."
    },
    {
        "doc_id": "346106034",
        "date": "2020.02.02."
    },
    {
        "doc_id": "346110644",
        "date": "2020.02.02."
    },
    {
        "doc_id": "346137761",
        "date": "2020.02.02."
    },
    {
        "doc_id": "346156898",
        "date": "2020.02.02."
    },
    {
        "doc_id": "346158990",
        "date": "2020.02.02."
    },
    {
        "doc_id": "346179301",
        "date": "2020.02.02."
    },
    {
        "doc_id": "346202724",
        "date": "2020.02.02."
    },
    {
        "doc_id": "346206643",
        "date": "2020.02.02."
    },
    {
        "doc_id": "345846750",
        "date": "2020.01.29."
    },
    {
        "doc_id": "345026776",
        "date": "2020.01.17."
    },
    {
        "doc_id": "344174998",
        "date": "2020.01.08."
    },
    {
        "doc_id": "343236053",
        "date": "2019.12.25."
    },
    {
        "doc_id": "320024453",
        "date": "2019.01.31."
    },
    {
        "doc_id": "320004235",
        "date": "2019.01.31."
    },
    {
        "doc_id": "319904215",
        "date": "2019.01.31."
    },
    {
        "doc_id": "320102701",
        "date": "2019.01.31."
    },
    {
        "doc_id": "309791347",
        "date": "2018.09.11."
    },
    {
        "doc_id": "304453304",
        "date": "2018.06.29."
    },
    {
        "doc_id": "303987804",
        "date": "2018.06.21."
    },
    {
        "doc_id": "299603533",
        "date": "2018.04.19."
    },
    {
        "doc_id": "297306806",
        "date": "2018.03.17."
    },
    {
        "doc_id": "294435691",
        "date": "2018.02.10."
    },
    {
        "doc_id": "294250494",
        "date": "2018.02.10."
    },
    {
        "doc_id": "294496398",
        "date": "2018.02.09."
    },
    {
        "doc_id": "294543239",
        "date": "2018.02.09."
    },
    {
        "doc_id": "294535336",
        "date": "2018.02.09."
    },
    {
        "doc_id": "294128493",
        "date": "2018.02.04."
    },
    {
        "doc_id": "294034309",
        "date": "2018.02.04."
    },
    {
        "doc_id": "293601076",
        "date": "2018.02.04."
    },
    {
        "doc_id": "294086353",
        "date": "2018.02.04."
    },
    {
        "doc_id": "294043652",
        "date": "2018.02.04."
    },
    {
        "doc_id": "294119480",
        "date": "2018.02.04."
    },
    {
        "doc_id": "294035039",
        "date": "2018.02.02."
    },
    {
        "doc_id": "293691814",
        "date": "2018.01.29."
    },
    {
        "doc_id": "293693644",
        "date": "2018.01.29."
    },
    {
        "doc_id": "292885373",
        "date": "2018.01.21."
    },
    {
        "doc_id": "292915221",
        "date": "2018.01.21."
    },
    {
        "doc_id": "292891757",
        "date": "2018.01.21."
    },
    {
        "doc_id": "292999651",
        "date": "2018.01.21."
    },
    {
        "doc_id": "292892903",
        "date": "2018.01.21."
    },
    {
        "doc_id": "292793537",
        "date": "2018.01.21."
    },
    {
        "doc_id": "292887188",
        "date": "2018.01.21."
    },
    {
        "doc_id": "291193072",
        "date": "2017.12.29."
    },
    {
        "doc_id": "291062480",
        "date": "2017.12.27."
    },
    {
        "doc_id": "291049282",
        "date": "2017.12.27."
    },
    {
        "doc_id": "291062216",
        "date": "2017.12.27."
    },
    {
        "doc_id": "290676259",
        "date": "2017.12.21."
    },
    {
        "doc_id": "290676768",
        "date": "2017.12.20."
    },
    {
        "doc_id": "288428465",
        "date": "2017.11.17."
    },
    {
        "doc_id": "283938321",
        "date": "2017.09.04."
    },
    {
        "doc_id": "280186830",
        "date": "2017.07.10."
    },
    {
        "doc_id": "280100881",
        "date": "2017.07.10."
    },
    {
        "doc_id": "280081051",
        "date": "2017.07.10."
    },
    {
        "doc_id": "280187488",
        "date": "2017.07.10."
    },
    {
        "doc_id": "280197388",
        "date": "2017.07.10."
    },
    {
        "doc_id": "280202444",
        "date": "2017.07.10."
    },
    {
        "doc_id": "280094617",
        "date": "2017.07.10."
    },
    {
        "doc_id": "280137397",
        "date": "2017.07.10."
    },
    {
        "doc_id": "280097668",
        "date": "2017.07.10."
    },
    {
        "doc_id": "280085070",
        "date": "2017.07.10."
    },
    {
        "doc_id": "278236354",
        "date": "2017.06.13."
    },
    {
        "doc_id": "278439157",
        "date": "2017.06.13."
    },
    {
        "doc_id": "278118633",
        "date": "2017.06.09."
    },
    {
        "doc_id": "278139654",
        "date": "2017.06.09."
    },
    {
        "doc_id": "278187424",
        "date": "2017.06.09."
    },
    {
        "doc_id": "278192302",
        "date": "2017.06.09."
    },
    {
        "doc_id": "277886076",
        "date": "2017.06.05."
    },
    {
        "doc_id": "277891118",
        "date": "2017.06.05."
    },
    {
        "doc_id": "277885202",
        "date": "2017.06.05."
    },
    {
        "doc_id": "277753834",
        "date": "2017.06.05."
    },
    {
        "doc_id": "277865657",
        "date": "2017.06.05."
    },
    {
        "doc_id": "276933705",
        "date": "2017.05.20."
    },
    {
        "doc_id": "276682536",
        "date": "2017.05.20."
    },
    {
        "doc_id": "276718063",
        "date": "2017.05.20."
    },
    {
        "doc_id": "276809304",
        "date": "2017.05.20."
    },
    {
        "doc_id": "276670332",
        "date": "2017.05.20."
    },
    {
        "doc_id": "276652956",
        "date": "2017.05.20."
    },
    {
        "doc_id": "275730517",
        "date": "2017.05.01."
    },
    {
        "doc_id": "275719032",
        "date": "2017.05.01."
    },
    {
        "doc_id": "275728434",
        "date": "2017.05.01."
    },
    {
        "doc_id": "270995529",
        "date": "2017.02.21."
    },
    {
        "doc_id": "270968514",
        "date": "2017.02.21."
    },
    {
        "doc_id": "270958622",
        "date": "2017.02.21."
    },
    {
        "doc_id": "270893053",
        "date": "2017.02.20."
    },
    {
        "doc_id": "270630908",
        "date": "2017.02.20."
    },
    {
        "doc_id": "271027052",
        "date": "2017.02.20."
    },
    {
        "doc_id": "271054075",
        "date": "2017.02.20."
    },
    {
        "doc_id": "271169376",
        "date": "2017.02.20."
    },
    {
        "doc_id": "270956045",
        "date": "2017.02.20."
    },
    {
        "doc_id": "270991431",
        "date": "2017.02.20."
    },
    {
        "doc_id": "270951280",
        "date": "2017.02.20."
    },
    {
        "doc_id": "271060190",
        "date": "2017.02.20."
    },
    {
        "doc_id": "270629784",
        "date": "2017.02.20."
    },
    {
        "doc_id": "271087786",
        "date": "2017.02.20."
    },
    {
        "doc_id": "270765674",
        "date": "2017.02.17."
    },
    {
        "doc_id": "270889882",
        "date": "2017.02.17."
    },
    {
        "doc_id": "270588050",
        "date": "2017.02.17."
    },
    {
        "doc_id": "270854695",
        "date": "2017.02.17."
    },
    {
        "doc_id": "270712764",
        "date": "2017.02.17."
    },
    {
        "doc_id": "270423156",
        "date": "2017.02.17."
    },
    {
        "doc_id": "270281763",
        "date": "2017.02.17."
    },
    {
        "doc_id": "270799580",
        "date": "2017.02.17."
    },
    {
        "doc_id": "270845892",
        "date": "2017.02.17."
    },
    {
        "doc_id": "270791698",
        "date": "2017.02.17."
    },
    {
        "doc_id": "270810783",
        "date": "2017.02.17."
    },
    {
        "doc_id": "270493541",
        "date": "2017.02.14."
    },
    {
        "doc_id": "270275210",
        "date": "2017.02.12."
    },
    {
        "doc_id": "270284191",
        "date": "2017.02.12."
    },
    {
        "doc_id": "270351640",
        "date": "2017.02.12."
    },
    {
        "doc_id": "270354367",
        "date": "2017.02.12."
    },
    {
        "doc_id": "270372506",
        "date": "2017.02.12."
    },
    {
        "doc_id": "270375489",
        "date": "2017.02.12."
    },
    {
        "doc_id": "270190277",
        "date": "2017.02.10."
    },
    {
        "doc_id": "270040406",
        "date": "2017.02.10."
    },
    {
        "doc_id": "270045860",
        "date": "2017.02.10."
    },
    {
        "doc_id": "270144618",
        "date": "2017.02.10."
    },
    {
        "doc_id": "270224455",
        "date": "2017.02.10."
    },
    {
        "doc_id": "270142217",
        "date": "2017.02.10."
    },
    {
        "doc_id": "270060720",
        "date": "2017.02.10."
    },
    {
        "doc_id": "270254076",
        "date": "2017.02.10."
    },
    {
        "doc_id": "269946028",
        "date": "2017.02.10."
    },
    {
        "doc_id": "269666794",
        "date": "2017.02.08."
    },
    {
        "doc_id": "269771221",
        "date": "2017.02.08."
    },
    {
        "doc_id": "269532874",
        "date": "2017.02.08."
    },
    {
        "doc_id": "269763728",
        "date": "2017.02.08."
    },
    {
        "doc_id": "269823499",
        "date": "2017.02.08."
    },
    {
        "doc_id": "269856361",
        "date": "2017.02.08."
    },
    {
        "doc_id": "269886801",
        "date": "2017.02.07."
    },
    {
        "doc_id": "269912127",
        "date": "2017.02.07."
    },
    {
        "doc_id": "269916184",
        "date": "2017.02.07."
    },
    {
        "doc_id": "269946938",
        "date": "2017.02.07."
    },
    {
        "doc_id": "269749352",
        "date": "2017.02.03."
    },
    {
        "doc_id": "269263040",
        "date": "2017.02.03."
    },
    {
        "doc_id": "269750709",
        "date": "2017.02.03."
    },
    {
        "doc_id": "269634956",
        "date": "2017.02.03."
    },
    {
        "doc_id": "269645706",
        "date": "2017.02.03."
    },
    {
        "doc_id": "269275830",
        "date": "2017.02.01."
    },
    {
        "doc_id": "269016764",
        "date": "2017.02.01."
    },
    {
        "doc_id": "269343436",
        "date": "2017.02.01."
    },
    {
        "doc_id": "269289970",
        "date": "2017.02.01."
    },
    {
        "doc_id": "269397632",
        "date": "2017.02.01."
    },
    {
        "doc_id": "269469023",
        "date": "2017.02.01."
    },
    {
        "doc_id": "269469181",
        "date": "2017.02.01."
    },
    {
        "doc_id": "269471942",
        "date": "2017.02.01."
    },
    {
        "doc_id": "268902763",
        "date": "2017.01.24."
    },
    {
        "doc_id": "268875088",
        "date": "2017.01.24."
    },
    {
        "doc_id": "268871774",
        "date": "2017.01.24."
    },
    {
        "doc_id": "268864922",
        "date": "2017.01.24."
    },
    {
        "doc_id": "268864125",
        "date": "2017.01.24."
    },
    {
        "doc_id": "268796223",
        "date": "2017.01.22."
    },
    {
        "doc_id": "268852707",
        "date": "2017.01.22."
    },
    {
        "doc_id": "268809058",
        "date": "2017.01.22."
    },
    {
        "doc_id": "268764815",
        "date": "2017.01.22."
    },
    {
        "doc_id": "268763259",
        "date": "2017.01.22."
    },
    {
        "doc_id": "268732523",
        "date": "2017.01.21."
    },
    {
        "doc_id": "268681420",
        "date": "2017.01.21."
    },
    {
        "doc_id": "268668422",
        "date": "2017.01.21."
    },
    {
        "doc_id": "268625013",
        "date": "2017.01.21."
    },
    {
        "doc_id": "268629042",
        "date": "2017.01.20."
    },
    {
        "doc_id": "268627400",
        "date": "2017.01.20."
    },
    {
        "doc_id": "268619349",
        "date": "2017.01.20."
    },
    {
        "doc_id": "268648231",
        "date": "2017.01.20."
    },
    {
        "doc_id": "268481764",
        "date": "2017.01.19."
    },
    {
        "doc_id": "268536306",
        "date": "2017.01.19."
    },
    {
        "doc_id": "268581206",
        "date": "2017.01.19."
    },
    {
        "doc_id": "268511454",
        "date": "2017.01.19."
    },
    {
        "doc_id": "268454911",
        "date": "2017.01.18."
    },
    {
        "doc_id": "268438269",
        "date": "2017.01.17."
    },
    {
        "doc_id": "268412151",
        "date": "2017.01.17."
    },
    {
        "doc_id": "268390189",
        "date": "2017.01.17."
    },
    {
        "doc_id": "268341446",
        "date": "2017.01.15."
    },
    {
        "doc_id": "268262233",
        "date": "2017.01.15."
    },
    {
        "doc_id": "268220603",
        "date": "2017.01.15."
    },
    {
        "doc_id": "268222884",
        "date": "2017.01.15."
    },
    {
        "doc_id": "268259042",
        "date": "2017.01.15."
    },
    {
        "doc_id": "268264159",
        "date": "2017.01.15."
    },
    {
        "doc_id": "268269163",
        "date": "2017.01.15."
    },
    {
        "doc_id": "267989710",
        "date": "2017.01.14."
    },
    {
        "doc_id": "268009922",
        "date": "2017.01.14."
    },
    {
        "doc_id": "268033904",
        "date": "2017.01.14."
    },
    {
        "doc_id": "268174779",
        "date": "2017.01.14."
    },
    {
        "doc_id": "267965915",
        "date": "2017.01.14."
    },
    {
        "doc_id": "267682437",
        "date": "2017.01.14."
    },
    {
        "doc_id": "267702394",
        "date": "2017.01.14."
    },
    {
        "doc_id": "268077811",
        "date": "2017.01.14."
    },
    {
        "doc_id": "268202051",
        "date": "2017.01.14."
    },
    {
        "doc_id": "267930315",
        "date": "2017.01.11."
    },
    {
        "doc_id": "267795240",
        "date": "2017.01.11."
    },
    {
        "doc_id": "267897980",
        "date": "2017.01.11."
    },
    {
        "doc_id": "267903502",
        "date": "2017.01.11."
    },
    {
        "doc_id": "267896585",
        "date": "2017.01.11."
    },
    {
        "doc_id": "267906147",
        "date": "2017.01.11."
    },
    {
        "doc_id": "267839282",
        "date": "2017.01.11."
    },
    {
        "doc_id": "267850295",
        "date": "2017.01.10."
    },
    {
        "doc_id": "267826049",
        "date": "2017.01.10."
    },
    {
        "doc_id": "267825985",
        "date": "2017.01.10."
    },
    {
        "doc_id": "267922941",
        "date": "2017.01.10."
    },
    {
        "doc_id": "267928096",
        "date": "2017.01.10."
    },
    {
        "doc_id": "267905252",
        "date": "2017.01.10."
    },
    {
        "doc_id": "267819422",
        "date": "2017.01.09."
    },
    {
        "doc_id": "267816415",
        "date": "2017.01.09."
    },
    {
        "doc_id": "267686206",
        "date": "2017.01.09."
    },
    {
        "doc_id": "267616964",
        "date": "2017.01.09."
    },
    {
        "doc_id": "267786378",
        "date": "2017.01.09."
    },
    {
        "doc_id": "267873772",
        "date": "2017.01.09."
    },
    {
        "doc_id": "267310483",
        "date": "2017.01.07."
    },
    {
        "doc_id": "267404530",
        "date": "2017.01.03."
    },
    {
        "doc_id": "267387388",
        "date": "2017.01.03."
    },
    {
        "doc_id": "267393863",
        "date": "2017.01.03."
    },
    {
        "doc_id": "267438871",
        "date": "2017.01.03."
    },
    {
        "doc_id": "267373423",
        "date": "2017.01.03."
    },
    {
        "doc_id": "267334657",
        "date": "2017.01.03."
    },
    {
        "doc_id": "267408682",
        "date": "2017.01.03."
    },
    {
        "doc_id": "267251466",
        "date": "2017.01.03."
    },
    {
        "doc_id": "267376583",
        "date": "2017.01.03."
    },
    {
        "doc_id": "267397514",
        "date": "2017.01.03."
    },
    {
        "doc_id": "267378991",
        "date": "2017.01.03."
    },
    {
        "doc_id": "267367566",
        "date": "2017.01.03."
    },
    {
        "doc_id": "267256506",
        "date": "2017.01.03."
    },
    {
        "doc_id": "267353040",
        "date": "2017.01.03."
    },
    {
        "doc_id": "267209664",
        "date": "2017.01.03."
    },
    {
        "doc_id": "267206139",
        "date": "2017.01.02."
    },
    {
        "doc_id": "267224008",
        "date": "2017.01.02."
    },
    {
        "doc_id": "267227291",
        "date": "2017.01.02."
    },
    {
        "doc_id": "267204723",
        "date": "2017.01.02."
    },
    {
        "doc_id": "267150597",
        "date": "2017.01.02."
    },
    {
        "doc_id": "267260558",
        "date": "2017.01.02."
    },
    {
        "doc_id": "267274575",
        "date": "2017.01.02."
    },
    {
        "doc_id": "267292226",
        "date": "2017.01.02."
    },
    {
        "doc_id": "267305565",
        "date": "2017.01.02."
    },
    {
        "doc_id": "267309354",
        "date": "2017.01.02."
    },
    {
        "doc_id": "267284061",
        "date": "2017.01.02."
    },
    {
        "doc_id": "267295203",
        "date": "2017.01.02."
    },
    {
        "doc_id": "267305219",
        "date": "2017.01.02."
    },
    {
        "doc_id": "267305987",
        "date": "2017.01.02."
    },
    {
        "doc_id": "267313591",
        "date": "2017.01.02."
    },
    {
        "doc_id": "267317260",
        "date": "2017.01.02."
    },
    {
        "doc_id": "266505932",
        "date": "2016.12.22."
    },
    {
        "doc_id": "266177177",
        "date": "2016.12.16."
    },
    {
        "doc_id": "265489827",
        "date": "2016.12.08."
    },
    {
        "doc_id": "265542424",
        "date": "2016.12.07."
    },
    {
        "doc_id": "265537359",
        "date": "2016.12.07."
    },
    {
        "doc_id": "265594875",
        "date": "2016.12.07."
    },
    {
        "doc_id": "265451971",
        "date": "2016.12.07."
    },
    {
        "doc_id": "265478082",
        "date": "2016.12.07."
    },
    {
        "doc_id": "265612499",
        "date": "2016.12.07."
    },
    {
        "doc_id": "265673029",
        "date": "2016.12.07."
    },
    {
        "doc_id": "265275372",
        "date": "2016.11.30."
    },
    {
        "doc_id": "265266892",
        "date": "2016.11.30."
    },
    {
        "doc_id": "265238793",
        "date": "2016.11.29."
    },
    {
        "doc_id": "265071113",
        "date": "2016.11.28."
    },
    {
        "doc_id": "265146336",
        "date": "2016.11.28."
    },
    {
        "doc_id": "265174639",
        "date": "2016.11.28."
    },
    {
        "doc_id": "265167215",
        "date": "2016.11.28."
    },
    {
        "doc_id": "265190041",
        "date": "2016.11.28."
    },
    {
        "doc_id": "264988904",
        "date": "2016.11.25."
    },
    {
        "doc_id": "264634873",
        "date": "2016.11.25."
    },
    {
        "doc_id": "264715081",
        "date": "2016.11.25."
    },
    {
        "doc_id": "264899643",
        "date": "2016.11.25."
    },
    {
        "doc_id": "264911224",
        "date": "2016.11.24."
    },
    {
        "doc_id": "264694622",
        "date": "2016.11.23."
    },
    {
        "doc_id": "264712752",
        "date": "2016.11.23."
    },
    {
        "doc_id": "264804136",
        "date": "2016.11.23."
    },
    {
        "doc_id": "264875206",
        "date": "2016.11.23."
    },
    {
        "doc_id": "264650289",
        "date": "2016.11.23."
    },
    {
        "doc_id": "264829894",
        "date": "2016.11.23."
    },
    {
        "doc_id": "261667476",
        "date": "2016.10.07."
    },
    {
        "doc_id": "261698254",
        "date": "2016.10.06."
    },
    {
        "doc_id": "261896978",
        "date": "2016.10.06."
    },
    {
        "doc_id": "261511016",
        "date": "2016.10.01."
    },
    {
        "doc_id": "261392473",
        "date": "2016.10.01."
    },
    {
        "doc_id": "258198768",
        "date": "2016.08.13."
    },
    {
        "doc_id": "258218131",
        "date": "2016.08.12."
    },
    {
        "doc_id": "258336666",
        "date": "2016.08.12."
    },
    {
        "doc_id": "258128214",
        "date": "2016.08.11."
    },
    {
        "doc_id": "257873326",
        "date": "2016.08.10."
    },
    {
        "doc_id": "257869547",
        "date": "2016.08.10."
    },
    {
        "doc_id": "256480335",
        "date": "2016.07.19."
    },
    {
        "doc_id": "256436723",
        "date": "2016.07.19."
    },
    {
        "doc_id": "256515594",
        "date": "2016.07.19."
    },
    {
        "doc_id": "256409494",
        "date": "2016.07.19."
    },
    {
        "doc_id": "256052141",
        "date": "2016.07.14."
    },
    {
        "doc_id": "253851162",
        "date": "2016.06.08."
    },
    {
        "doc_id": "253827379",
        "date": "2016.06.08."
    },
    {
        "doc_id": "253801217",
        "date": "2016.06.08."
    },
    {
        "doc_id": "253814297",
        "date": "2016.06.08."
    },
    {
        "doc_id": "253899824",
        "date": "2016.06.08."
    },
    {
        "doc_id": "253793136",
        "date": "2016.06.08."
    },
    {
        "doc_id": "253858193",
        "date": "2016.06.08."
    },
    {
        "doc_id": "249592420",
        "date": "2016.04.06."
    },
    {
        "doc_id": "246745670",
        "date": "2016.02.27."
    },
    {
        "doc_id": "246621085",
        "date": "2016.02.27."
    },
    {
        "doc_id": "244478278",
        "date": "2016.02.02."
    },
    {
        "doc_id": "243838742",
        "date": "2016.01.25."
    },
    {
        "doc_id": "243797904",
        "date": "2016.01.25."
    },
    {
        "doc_id": "243747202",
        "date": "2016.01.25."
    },
    {
        "doc_id": "243689817",
        "date": "2016.01.25."
    },
    {
        "doc_id": "243499487",
        "date": "2016.01.25."
    },
    {
        "doc_id": "243389499",
        "date": "2016.01.25."
    },
    {
        "doc_id": "238562047",
        "date": "2015.11.16."
    },
    {
        "doc_id": "238088842",
        "date": "2015.11.10."
    },
    {
        "doc_id": "234448325",
        "date": "2015.09.16."
    },
    {
        "doc_id": "234099874",
        "date": "2015.09.16."
    },
    {
        "doc_id": "233292587",
        "date": "2015.09.01."
    },
    {
        "doc_id": "232046804",
        "date": "2015.08.21."
    },
    {
        "doc_id": "232459689",
        "date": "2015.08.21."
    },
    {
        "doc_id": "231714216",
        "date": "2015.08.12."
    },
    {
        "doc_id": "231357841",
        "date": "2015.08.12."
    },
    {
        "doc_id": "231803331",
        "date": "2015.08.12."
    },
    {
        "doc_id": "231807014",
        "date": "2015.08.12."
    },
    {
        "doc_id": "231716811",
        "date": "2015.08.12."
    },
    {
        "doc_id": "231563941",
        "date": "2015.08.11."
    },
    {
        "doc_id": "231543923",
        "date": "2015.08.10."
    },
    {
        "doc_id": "231517970",
        "date": "2015.08.10."
    },
    {
        "doc_id": "231187881",
        "date": "2015.08.05."
    },
    {
        "doc_id": "231218959",
        "date": "2015.08.05."
    },
    {
        "doc_id": "231223803",
        "date": "2015.08.05."
    },
    {
        "doc_id": "231042408",
        "date": "2015.08.03."
    },
    {
        "doc_id": "230974567",
        "date": "2015.08.03."
    },
    {
        "doc_id": "230958876",
        "date": "2015.08.03."
    },
    {
        "doc_id": "230946647",
        "date": "2015.08.03."
    },
    {
        "doc_id": "231029432",
        "date": "2015.08.03."
    },
    {
        "doc_id": "230579885",
        "date": "2015.08.01."
    },
    {
        "doc_id": "230362491",
        "date": "2015.07.28."
    },
    {
        "doc_id": "230345170",
        "date": "2015.07.28."
    },
    {
        "doc_id": "230392897",
        "date": "2015.07.28."
    },
    {
        "doc_id": "230493057",
        "date": "2015.07.28."
    },
    {
        "doc_id": "229817914",
        "date": "2015.07.24."
    },
    {
        "doc_id": "229942865",
        "date": "2015.07.24."
    },
    {
        "doc_id": "229849528",
        "date": "2015.07.24."
    },
    {
        "doc_id": "229999935",
        "date": "2015.07.24."
    },
    {
        "doc_id": "229898417",
        "date": "2015.07.24."
    },
    {
        "doc_id": "229862292",
        "date": "2015.07.24."
    },
    {
        "doc_id": "230235342",
        "date": "2015.07.24."
    },
    {
        "doc_id": "229361061",
        "date": "2015.07.17."
    },
    {
        "doc_id": "229585117",
        "date": "2015.07.15."
    },
    {
        "doc_id": "229533418",
        "date": "2015.07.14."
    },
    {
        "doc_id": "229392309",
        "date": "2015.07.14."
    },
    {
        "doc_id": "229403364",
        "date": "2015.07.14."
    },
    {
        "doc_id": "229084900",
        "date": "2015.07.10."
    },
    {
        "doc_id": "227731548",
        "date": "2015.06.23."
    },
    {
        "doc_id": "227991999",
        "date": "2015.06.23."
    },
    {
        "doc_id": "227324890",
        "date": "2015.06.16."
    },
    {
        "doc_id": "226548273",
        "date": "2015.06.04."
    },
    {
        "doc_id": "225849481",
        "date": "2015.05.27."
    },
    {
        "doc_id": "225791157",
        "date": "2015.05.27."
    },
    {
        "doc_id": "225617378",
        "date": "2015.05.22."
    },
    {
        "doc_id": "223281894",
        "date": "2015.04.25."
    },
    {
        "doc_id": "223122770",
        "date": "2015.04.25."
    },
    {
        "doc_id": "223604106",
        "date": "2015.04.24."
    },
    {
        "doc_id": "223537189",
        "date": "2015.04.23."
    },
    {
        "doc_id": "223525724",
        "date": "2015.04.23."
    },
    {
        "doc_id": "222748378",
        "date": "2015.04.14."
    },
    {
        "doc_id": "222742134",
        "date": "2015.04.14."
    },
    {
        "doc_id": "222603996",
        "date": "2015.04.14."
    },
    {
        "doc_id": "221599384",
        "date": "2015.04.04."
    },
    {
        "doc_id": "221732668",
        "date": "2015.04.04."
    },
    {
        "doc_id": "220979497",
        "date": "2015.03.20."
    },
    {
        "doc_id": "221010758",
        "date": "2015.03.20."
    },
    {
        "doc_id": "220075832",
        "date": "2015.03.09."
    },
    {
        "doc_id": "220111654",
        "date": "2015.03.09."
    },
    {
        "doc_id": "220149136",
        "date": "2015.03.09."
    },
    {
        "doc_id": "220156662",
        "date": "2015.03.09."
    },
    {
        "doc_id": "220006855",
        "date": "2015.03.07."
    },
    {
        "doc_id": "219968416",
        "date": "2015.03.07."
    },
    {
        "doc_id": "219975016",
        "date": "2015.03.07."
    },
    {
        "doc_id": "219977511",
        "date": "2015.03.07."
    },
    {
        "doc_id": "219981685",
        "date": "2015.03.07."
    },
    {
        "doc_id": "219504713",
        "date": "2015.03.02."
    },
    {
        "doc_id": "219669923",
        "date": "2015.03.02."
    },
    {
        "doc_id": "219379918",
        "date": "2015.03.02."
    },
    {
        "doc_id": "219203368",
        "date": "2015.03.02."
    },
    {
        "doc_id": "218764528",
        "date": "2015.02.27."
    },
    {
        "doc_id": "218960659",
        "date": "2015.02.26."
    },
    {
        "doc_id": "218961891",
        "date": "2015.02.26."
    },
    {
        "doc_id": "218019269",
        "date": "2015.02.12."
    },
    {
        "doc_id": "218020322",
        "date": "2015.02.12."
    },
    {
        "doc_id": "218008763",
        "date": "2015.02.12."
    },
    {
        "doc_id": "218002941",
        "date": "2015.02.12."
    },
    {
        "doc_id": "217999163",
        "date": "2015.02.12."
    },
    {
        "doc_id": "217996605",
        "date": "2015.02.12."
    },
    {
        "doc_id": "217787274",
        "date": "2015.02.10."
    },
    {
        "doc_id": "217380843",
        "date": "2015.02.10."
    },
    {
        "doc_id": "217316956",
        "date": "2015.02.10."
    },
    {
        "doc_id": "217751020",
        "date": "2015.02.10."
    },
    {
        "doc_id": "217429441",
        "date": "2015.02.06."
    },
    {
        "doc_id": "217399110",
        "date": "2015.02.06."
    },
    {
        "doc_id": "217414977",
        "date": "2015.02.06."
    },
    {
        "doc_id": "217153974",
        "date": "2015.02.04."
    },
    {
        "doc_id": "217146588",
        "date": "2015.02.04."
    },
    {
        "doc_id": "217145664",
        "date": "2015.02.04."
    },
    {
        "doc_id": "217080234",
        "date": "2015.02.04."
    },
    {
        "doc_id": "216759369",
        "date": "2015.01.30."
    },
    {
        "doc_id": "216778945",
        "date": "2015.01.30."
    },
    {
        "doc_id": "216689664",
        "date": "2015.01.30."
    },
    {
        "doc_id": "216784445",
        "date": "2015.01.30."
    },
    {
        "doc_id": "216726156",
        "date": "2015.01.30."
    },
    {
        "doc_id": "216741971",
        "date": "2015.01.30."
    },
    {
        "doc_id": "216661555",
        "date": "2015.01.30."
    },
    {
        "doc_id": "216785034",
        "date": "2015.01.30."
    },
    {
        "doc_id": "216181073",
        "date": "2015.01.30."
    },
    {
        "doc_id": "216687529",
        "date": "2015.01.30."
    },
    {
        "doc_id": "216339036",
        "date": "2015.01.29."
    },
    {
        "doc_id": "216639083",
        "date": "2015.01.29."
    },
    {
        "doc_id": "216703051",
        "date": "2015.01.29."
    },
    {
        "doc_id": "216769172",
        "date": "2015.01.29."
    },
    {
        "doc_id": "216786740",
        "date": "2015.01.29."
    },
    {
        "doc_id": "216793906",
        "date": "2015.01.29."
    },
    {
        "doc_id": "216321977",
        "date": "2015.01.26."
    },
    {
        "doc_id": "216173092",
        "date": "2015.01.26."
    },
    {
        "doc_id": "215470215",
        "date": "2015.01.21."
    },
    {
        "doc_id": "215905880",
        "date": "2015.01.21."
    },
    {
        "doc_id": "215909350",
        "date": "2015.01.21."
    },
    {
        "doc_id": "214949647",
        "date": "2015.01.14."
    },
    {
        "doc_id": "215048955",
        "date": "2015.01.14."
    },
    {
        "doc_id": "215034170",
        "date": "2015.01.14."
    },
    {
        "doc_id": "214901029",
        "date": "2015.01.13."
    },
    {
        "doc_id": "215262136",
        "date": "2015.01.13."
    },
    {
        "doc_id": "215058154",
        "date": "2015.01.13."
    },
    {
        "doc_id": "214976370",
        "date": "2015.01.13."
    },
    {
        "doc_id": "215060523",
        "date": "2015.01.13."
    },
    {
        "doc_id": "215124837",
        "date": "2015.01.13."
    },
    {
        "doc_id": "215241154",
        "date": "2015.01.13."
    },
    {
        "doc_id": "215304069",
        "date": "2015.01.13."
    },
    {
        "doc_id": "214819714",
        "date": "2015.01.13."
    },
    {
        "doc_id": "214836346",
        "date": "2015.01.08."
    },
    {
        "doc_id": "214786276",
        "date": "2015.01.07."
    },
    {
        "doc_id": "214601685",
        "date": "2015.01.06."
    },
    {
        "doc_id": "214614919",
        "date": "2015.01.06."
    },
    {
        "doc_id": "214535416",
        "date": "2015.01.06."
    },
    {
        "doc_id": "214425461",
        "date": "2015.01.06."
    },
    {
        "doc_id": "214613370",
        "date": "2015.01.06."
    },
    {
        "doc_id": "214269327",
        "date": "2015.01.06."
    },
    {
        "doc_id": "214619413",
        "date": "2015.01.06."
    },
    {
        "doc_id": "214590507",
        "date": "2015.01.06."
    },
    {
        "doc_id": "214421992",
        "date": "2015.01.03."
    },
    {
        "doc_id": "214405687",
        "date": "2015.01.03."
    },
    {
        "doc_id": "214424039",
        "date": "2015.01.03."
    },
    {
        "doc_id": "214146398",
        "date": "2015.01.03."
    },
    {
        "doc_id": "214393463",
        "date": "2015.01.03."
    },
    {
        "doc_id": "214387663",
        "date": "2015.01.03."
    },
    {
        "doc_id": "214397980",
        "date": "2015.01.03."
    },
    {
        "doc_id": "213984523",
        "date": "2015.01.03."
    },
    {
        "doc_id": "214385159",
        "date": "2015.01.03."
    },
    {
        "doc_id": "214330825",
        "date": "2015.01.03."
    },
    {
        "doc_id": "213981071",
        "date": "2015.01.03."
    },
    {
        "doc_id": "213854852",
        "date": "2015.01.01."
    },
    {
        "doc_id": "213865383",
        "date": "2015.01.01."
    },
    {
        "doc_id": "214066650",
        "date": "2015.01.01."
    },
    {
        "doc_id": "213854685",
        "date": "2015.01.01."
    },
    {
        "doc_id": "213832390",
        "date": "2015.01.01."
    },
    {
        "doc_id": "213762852",
        "date": "2015.01.01."
    },
    {
        "doc_id": "213806837",
        "date": "2014.12.31."
    },
    {
        "doc_id": "213855224",
        "date": "2014.12.31."
    },
    {
        "doc_id": "214138982",
        "date": "2014.12.31."
    },
    {
        "doc_id": "214052981",
        "date": "2014.12.30."
    },
    {
        "doc_id": "214052364",
        "date": "2014.12.30."
    },
    {
        "doc_id": "214132273",
        "date": "2014.12.30."
    },
    {
        "doc_id": "214103195",
        "date": "2014.12.30."
    },
    {
        "doc_id": "213780573",
        "date": "2014.12.30."
    },
    {
        "doc_id": "213911625",
        "date": "2014.12.30."
    },
    {
        "doc_id": "213760753",
        "date": "2014.12.30."
    },
    {
        "doc_id": "213835412",
        "date": "2014.12.30."
    },
    {
        "doc_id": "213570071",
        "date": "2014.12.30."
    },
    {
        "doc_id": "213838151",
        "date": "2014.12.30."
    },
    {
        "doc_id": "214086434",
        "date": "2014.12.30."
    },
    {
        "doc_id": "214050005",
        "date": "2014.12.29."
    },
    {
        "doc_id": "213758829",
        "date": "2014.12.29."
    },
    {
        "doc_id": "213770832",
        "date": "2014.12.29."
    },
    {
        "doc_id": "213870474",
        "date": "2014.12.29."
    },
    {
        "doc_id": "214000693",
        "date": "2014.12.29."
    },
    {
        "doc_id": "213901510",
        "date": "2014.12.29."
    },
    {
        "doc_id": "213902033",
        "date": "2014.12.29."
    },
    {
        "doc_id": "214049118",
        "date": "2014.12.29."
    },
    {
        "doc_id": "214005164",
        "date": "2014.12.29."
    },
    {
        "doc_id": "213841260",
        "date": "2014.12.27."
    },
    {
        "doc_id": "213850503",
        "date": "2014.12.26."
    },
    {
        "doc_id": "213561470",
        "date": "2014.12.26."
    },
    {
        "doc_id": "213534979",
        "date": "2014.12.24."
    },
    {
        "doc_id": "213499067",
        "date": "2014.12.24."
    },
    {
        "doc_id": "213445668",
        "date": "2014.12.24."
    },
    {
        "doc_id": "213499602",
        "date": "2014.12.24."
    },
    {
        "doc_id": "213474236",
        "date": "2014.12.24."
    },
    {
        "doc_id": "213433786",
        "date": "2014.12.24."
    },
    {
        "doc_id": "213708102",
        "date": "2014.12.24."
    },
    {
        "doc_id": "213652449",
        "date": "2014.12.24."
    },
    {
        "doc_id": "213425659",
        "date": "2014.12.24."
    },
    {
        "doc_id": "213652058",
        "date": "2014.12.24."
    },
    {
        "doc_id": "213469223",
        "date": "2014.12.24."
    },
    {
        "doc_id": "213475928",
        "date": "2014.12.24."
    },
    {
        "doc_id": "213440415",
        "date": "2014.12.24."
    },
    {
        "doc_id": "213430779",
        "date": "2014.12.23."
    },
    {
        "doc_id": "213430571",
        "date": "2014.12.23."
    },
    {
        "doc_id": "213596363",
        "date": "2014.12.22."
    },
    {
        "doc_id": "213545544",
        "date": "2014.12.21."
    },
    {
        "doc_id": "213552652",
        "date": "2014.12.21."
    },
    {
        "doc_id": "213554952",
        "date": "2014.12.21."
    },
    {
        "doc_id": "213209195",
        "date": "2014.12.21."
    },
    {
        "doc_id": "213558523",
        "date": "2014.12.21."
    },
    {
        "doc_id": "213067331",
        "date": "2014.12.19."
    },
    {
        "doc_id": "212716294",
        "date": "2014.12.18."
    },
    {
        "doc_id": "211379740",
        "date": "2014.11.25."
    },
    {
        "doc_id": "211590721",
        "date": "2014.11.25."
    },
    {
        "doc_id": "210513209",
        "date": "2014.11.15."
    },
    {
        "doc_id": "210431865",
        "date": "2014.11.15."
    },
    {
        "doc_id": "210425403",
        "date": "2014.11.11."
    },
    {
        "doc_id": "210504055",
        "date": "2014.11.11."
    },
    {
        "doc_id": "210525263",
        "date": "2014.11.11."
    },
    {
        "doc_id": "210536589",
        "date": "2014.11.11."
    },
    {
        "doc_id": "210163681",
        "date": "2014.11.04."
    },
    {
        "doc_id": "209763932",
        "date": "2014.10.30."
    },
    {
        "doc_id": "209746582",
        "date": "2014.10.30."
    },
    {
        "doc_id": "209308409",
        "date": "2014.10.28."
    },
    {
        "doc_id": "209692429",
        "date": "2014.10.28."
    },
    {
        "doc_id": "209698734",
        "date": "2014.10.28."
    },
    {
        "doc_id": "202127677",
        "date": "2014.07.16."
    },
    {
        "doc_id": "202138577",
        "date": "2014.07.16."
    },
    {
        "doc_id": "201862587",
        "date": "2014.07.11."
    },
    {
        "doc_id": "201086649",
        "date": "2014.06.30."
    },
    {
        "doc_id": "200596709",
        "date": "2014.06.25."
    },
    {
        "doc_id": "200363718",
        "date": "2014.06.25."
    },
    {
        "doc_id": "200361507",
        "date": "2014.06.21."
    },
    {
        "doc_id": "200096652",
        "date": "2014.06.17."
    },
    {
        "doc_id": "199966237",
        "date": "2014.06.17."
    },
    {
        "doc_id": "199890231",
        "date": "2014.06.16."
    },
    {
        "doc_id": "199862226",
        "date": "2014.06.16."
    },
    {
        "doc_id": "199275329",
        "date": "2014.06.13."
    },
    {
        "doc_id": "199275242",
        "date": "2014.06.13."
    },
    {
        "doc_id": "199797300",
        "date": "2014.06.12."
    },
    {
        "doc_id": "199588560",
        "date": "2014.06.10."
    },
    {
        "doc_id": "199583484",
        "date": "2014.06.10."
    },
    {
        "doc_id": "199239978",
        "date": "2014.06.05."
    },
    {
        "doc_id": "199257997",
        "date": "2014.06.05."
    },
    {
        "doc_id": "199275272",
        "date": "2014.06.05."
    },
    {
        "doc_id": "199007180",
        "date": "2014.06.04."
    },
    {
        "doc_id": "198967478",
        "date": "2014.06.04."
    },
    {
        "doc_id": "198953669",
        "date": "2014.06.04."
    },
    {
        "doc_id": "198607428",
        "date": "2014.05.30."
    },
    {
        "doc_id": "198729822",
        "date": "2014.05.30."
    },
    {
        "doc_id": "198730755",
        "date": "2014.05.30."
    },
    {
        "doc_id": "198549726",
        "date": "2014.05.27."
    },
    {
        "doc_id": "198014516",
        "date": "2014.05.20."
    },
    {
        "doc_id": "197997231",
        "date": "2014.05.20."
    },
    {
        "doc_id": "197940023",
        "date": "2014.05.20."
    },
    {
        "doc_id": "197968641",
        "date": "2014.05.20."
    },
    {
        "doc_id": "197839305",
        "date": "2014.05.18."
    },
    {
        "doc_id": "197564342",
        "date": "2014.05.15."
    },
    {
        "doc_id": "196800393",
        "date": "2014.05.02."
    },
    {
        "doc_id": "196223434",
        "date": "2014.04.25."
    },
    {
        "doc_id": "196101812",
        "date": "2014.04.23."
    }
]