[
    {
        "doc_id": "257746697",
        "date": "2016.08.04."
    },
    {
        "doc_id": "257671241",
        "date": "2016.08.03."
    },
    {
        "doc_id": "246371538",
        "date": "2016.02.23."
    },
    {
        "doc_id": "246369663",
        "date": "2016.02.23."
    },
    {
        "doc_id": "242317454",
        "date": "2016.01.07."
    },
    {
        "doc_id": "231143961",
        "date": "2015.08.04."
    },
    {
        "doc_id": "219498516",
        "date": "2015.03.02."
    },
    {
        "doc_id": "219605143",
        "date": "2015.03.02."
    },
    {
        "doc_id": "219587848",
        "date": "2015.03.02."
    },
    {
        "doc_id": "219298309",
        "date": "2015.03.02."
    },
    {
        "doc_id": "219575048",
        "date": "2015.03.01."
    },
    {
        "doc_id": "219419459",
        "date": "2015.03.01."
    },
    {
        "doc_id": "219573572",
        "date": "2015.03.01."
    },
    {
        "doc_id": "217443473",
        "date": "2015.02.05."
    },
    {
        "doc_id": "217445947",
        "date": "2015.02.05."
    },
    {
        "doc_id": "216671039",
        "date": "2015.01.28."
    },
    {
        "doc_id": "216682159",
        "date": "2015.01.28."
    },
    {
        "doc_id": "214685507",
        "date": "2015.01.08."
    },
    {
        "doc_id": "214840671",
        "date": "2015.01.08."
    },
    {
        "doc_id": "214833604",
        "date": "2015.01.08."
    },
    {
        "doc_id": "214838044",
        "date": "2015.01.08."
    },
    {
        "doc_id": "213089294",
        "date": "2014.12.15."
    },
    {
        "doc_id": "213091115",
        "date": "2014.12.15."
    },
    {
        "doc_id": "212744210",
        "date": "2014.12.11."
    },
    {
        "doc_id": "212795483",
        "date": "2014.12.11."
    },
    {
        "doc_id": "212580264",
        "date": "2014.12.11."
    },
    {
        "doc_id": "208887970",
        "date": "2014.10.15."
    },
    {
        "doc_id": "208884768",
        "date": "2014.10.15."
    },
    {
        "doc_id": "208836531",
        "date": "2014.10.15."
    },
    {
        "doc_id": "208771114",
        "date": "2014.10.15."
    },
    {
        "doc_id": "208886003",
        "date": "2014.10.15."
    },
    {
        "doc_id": "208820515",
        "date": "2014.10.15."
    },
    {
        "doc_id": "208876760",
        "date": "2014.10.15."
    },
    {
        "doc_id": "206468507",
        "date": "2014.09.11."
    },
    {
        "doc_id": "206469177",
        "date": "2014.09.11."
    },
    {
        "doc_id": "205304271",
        "date": "2014.08.25."
    },
    {
        "doc_id": "205160236",
        "date": "2014.08.23."
    },
    {
        "doc_id": "205202672",
        "date": "2014.08.23."
    },
    {
        "doc_id": "205203919",
        "date": "2014.08.23."
    },
    {
        "doc_id": "204879941",
        "date": "2014.08.21."
    },
    {
        "doc_id": "205029964",
        "date": "2014.08.21."
    },
    {
        "doc_id": "205030682",
        "date": "2014.08.21."
    },
    {
        "doc_id": "204667755",
        "date": "2014.08.21."
    },
    {
        "doc_id": "204731833",
        "date": "2014.08.21."
    },
    {
        "doc_id": "204669399",
        "date": "2014.08.18."
    },
    {
        "doc_id": "204715574",
        "date": "2014.08.18."
    },
    {
        "doc_id": "204759934",
        "date": "2014.08.18."
    },
    {
        "doc_id": "204763628",
        "date": "2014.08.18."
    },
    {
        "doc_id": "204703072",
        "date": "2014.08.17."
    },
    {
        "doc_id": "204705575",
        "date": "2014.08.17."
    },
    {
        "doc_id": "204697897",
        "date": "2014.08.17."
    },
    {
        "doc_id": "203698963",
        "date": "2014.08.07."
    },
    {
        "doc_id": "203470573",
        "date": "2014.08.07."
    },
    {
        "doc_id": "203469168",
        "date": "2014.08.02."
    },
    {
        "doc_id": "203482279",
        "date": "2014.08.02."
    },
    {
        "doc_id": "202289673",
        "date": "2014.07.17."
    },
    {
        "doc_id": "202070893",
        "date": "2014.07.17."
    },
    {
        "doc_id": "202080908",
        "date": "2014.07.17."
    },
    {
        "doc_id": "201671763",
        "date": "2014.07.09."
    },
    {
        "doc_id": "201680968",
        "date": "2014.07.09."
    },
    {
        "doc_id": "201725092",
        "date": "2014.07.09."
    },
    {
        "doc_id": "201715565",
        "date": "2014.07.09."
    },
    {
        "doc_id": "200864525",
        "date": "2014.06.27."
    },
    {
        "doc_id": "200660008",
        "date": "2014.06.27."
    },
    {
        "doc_id": "200487496",
        "date": "2014.06.27."
    },
    {
        "doc_id": "200392756",
        "date": "2014.06.27."
    },
    {
        "doc_id": "200261928",
        "date": "2014.06.20."
    },
    {
        "doc_id": "200295016",
        "date": "2014.06.20."
    },
    {
        "doc_id": "200161972",
        "date": "2014.06.20."
    },
    {
        "doc_id": "199679567",
        "date": "2014.06.10."
    },
    {
        "doc_id": "199681440",
        "date": "2014.06.10."
    },
    {
        "doc_id": "199598415",
        "date": "2014.06.10."
    },
    {
        "doc_id": "199204414",
        "date": "2014.06.10."
    },
    {
        "doc_id": "198771513",
        "date": "2014.05.29."
    },
    {
        "doc_id": "196489948",
        "date": "2014.04.27."
    },
    {
        "doc_id": "196490975",
        "date": "2014.04.27."
    },
    {
        "doc_id": "196487328",
        "date": "2014.04.27."
    },
    {
        "doc_id": "195152941",
        "date": "2014.04.08."
    },
    {
        "doc_id": "195127759",
        "date": "2014.04.08."
    },
    {
        "doc_id": "195117372",
        "date": "2014.04.08."
    },
    {
        "doc_id": "194671639",
        "date": "2014.04.08."
    },
    {
        "doc_id": "194179858",
        "date": "2014.03.25."
    },
    {
        "doc_id": "194185791",
        "date": "2014.03.25."
    },
    {
        "doc_id": "193410898",
        "date": "2014.03.17."
    },
    {
        "doc_id": "193614358",
        "date": "2014.03.17."
    },
    {
        "doc_id": "193614280",
        "date": "2014.03.17."
    },
    {
        "doc_id": "193109142",
        "date": "2014.03.17."
    },
    {
        "doc_id": "193606970",
        "date": "2014.03.17."
    },
    {
        "doc_id": "192780292",
        "date": "2014.03.11."
    },
    {
        "doc_id": "193183261",
        "date": "2014.03.11."
    },
    {
        "doc_id": "192260051",
        "date": "2014.02.27."
    },
    {
        "doc_id": "192269659",
        "date": "2014.02.27."
    },
    {
        "doc_id": "192272852",
        "date": "2014.02.27."
    },
    {
        "doc_id": "191927111",
        "date": "2014.02.24."
    },
    {
        "doc_id": "191147629",
        "date": "2014.02.14."
    },
    {
        "doc_id": "191055607",
        "date": "2014.02.13."
    },
    {
        "doc_id": "191050561",
        "date": "2014.02.13."
    },
    {
        "doc_id": "190984125",
        "date": "2014.02.13."
    },
    {
        "doc_id": "191064643",
        "date": "2014.02.13."
    },
    {
        "doc_id": "191064471",
        "date": "2014.02.13."
    },
    {
        "doc_id": "191058455",
        "date": "2014.02.13."
    },
    {
        "doc_id": "190723037",
        "date": "2014.02.13."
    },
    {
        "doc_id": "190718403",
        "date": "2014.02.13."
    },
    {
        "doc_id": "190964253",
        "date": "2014.02.13."
    },
    {
        "doc_id": "191043761",
        "date": "2014.02.13."
    },
    {
        "doc_id": "190558164",
        "date": "2014.02.07."
    },
    {
        "doc_id": "190581396",
        "date": "2014.02.07."
    },
    {
        "doc_id": "190588913",
        "date": "2014.02.07."
    },
    {
        "doc_id": "190588865",
        "date": "2014.02.07."
    },
    {
        "doc_id": "190588877",
        "date": "2014.02.07."
    },
    {
        "doc_id": "190589945",
        "date": "2014.02.07."
    },
    {
        "doc_id": "190492940",
        "date": "2014.02.06."
    },
    {
        "doc_id": "188097316",
        "date": "2014.01.07."
    },
    {
        "doc_id": "188105686",
        "date": "2014.01.07."
    },
    {
        "doc_id": "188106195",
        "date": "2014.01.07."
    },
    {
        "doc_id": "188107804",
        "date": "2014.01.07."
    },
    {
        "doc_id": "188109452",
        "date": "2014.01.07."
    },
    {
        "doc_id": "187867067",
        "date": "2014.01.04."
    },
    {
        "doc_id": "187854887",
        "date": "2014.01.04."
    },
    {
        "doc_id": "187887817",
        "date": "2014.01.04."
    },
    {
        "doc_id": "187899287",
        "date": "2014.01.04."
    },
    {
        "doc_id": "187808794",
        "date": "2014.01.03."
    },
    {
        "doc_id": "187811763",
        "date": "2014.01.03."
    },
    {
        "doc_id": "187815612",
        "date": "2014.01.03."
    },
    {
        "doc_id": "187699037",
        "date": "2014.01.02."
    },
    {
        "doc_id": "187702376",
        "date": "2014.01.02."
    },
    {
        "doc_id": "187232781",
        "date": "2013.12.26."
    },
    {
        "doc_id": "187171360",
        "date": "2013.12.25."
    },
    {
        "doc_id": "187170286",
        "date": "2013.12.25."
    },
    {
        "doc_id": "187203028",
        "date": "2013.12.25."
    },
    {
        "doc_id": "187205304",
        "date": "2013.12.25."
    },
    {
        "doc_id": "187210121",
        "date": "2013.12.25."
    },
    {
        "doc_id": "187210435",
        "date": "2013.12.25."
    },
    {
        "doc_id": "187200647",
        "date": "2013.12.25."
    },
    {
        "doc_id": "187198552",
        "date": "2013.12.25."
    },
    {
        "doc_id": "186334371",
        "date": "2013.12.12."
    },
    {
        "doc_id": "186363772",
        "date": "2013.12.12."
    },
    {
        "doc_id": "186225811",
        "date": "2013.12.10."
    },
    {
        "doc_id": "186220855",
        "date": "2013.12.10."
    },
    {
        "doc_id": "186223966",
        "date": "2013.12.10."
    },
    {
        "doc_id": "185879468",
        "date": "2013.12.05."
    },
    {
        "doc_id": "185879867",
        "date": "2013.12.05."
    },
    {
        "doc_id": "184840769",
        "date": "2013.11.19."
    },
    {
        "doc_id": "184811462",
        "date": "2013.11.19."
    },
    {
        "doc_id": "184835008",
        "date": "2013.11.19."
    },
    {
        "doc_id": "184833650",
        "date": "2013.11.19."
    },
    {
        "doc_id": "184669359",
        "date": "2013.11.18."
    },
    {
        "doc_id": "184682211",
        "date": "2013.11.18."
    },
    {
        "doc_id": "184683961",
        "date": "2013.11.18."
    },
    {
        "doc_id": "184758612",
        "date": "2013.11.18."
    },
    {
        "doc_id": "184759987",
        "date": "2013.11.18."
    },
    {
        "doc_id": "184404579",
        "date": "2013.11.12."
    },
    {
        "doc_id": "183943205",
        "date": "2013.11.05."
    },
    {
        "doc_id": "183840872",
        "date": "2013.11.04."
    },
    {
        "doc_id": "183848130",
        "date": "2013.11.04."
    },
    {
        "doc_id": "183687786",
        "date": "2013.11.01."
    },
    {
        "doc_id": "183522883",
        "date": "2013.10.29."
    },
    {
        "doc_id": "183534601",
        "date": "2013.10.29."
    },
    {
        "doc_id": "182283771",
        "date": "2013.10.11."
    },
    {
        "doc_id": "181724990",
        "date": "2013.10.04."
    },
    {
        "doc_id": "181746045",
        "date": "2013.10.04."
    },
    {
        "doc_id": "181776691",
        "date": "2013.10.04."
    },
    {
        "doc_id": "181808157",
        "date": "2013.10.04."
    },
    {
        "doc_id": "181816539",
        "date": "2013.10.04."
    },
    {
        "doc_id": "181818197",
        "date": "2013.10.04."
    },
    {
        "doc_id": "181311949",
        "date": "2013.10.01."
    },
    {
        "doc_id": "181459302",
        "date": "2013.10.01."
    },
    {
        "doc_id": "181602538",
        "date": "2013.10.01."
    },
    {
        "doc_id": "181603177",
        "date": "2013.10.01."
    },
    {
        "doc_id": "181051105",
        "date": "2013.09.23."
    },
    {
        "doc_id": "180555518",
        "date": "2013.09.17."
    },
    {
        "doc_id": "180730980",
        "date": "2013.09.17."
    },
    {
        "doc_id": "180532575",
        "date": "2013.09.17."
    },
    {
        "doc_id": "180614182",
        "date": "2013.09.17."
    },
    {
        "doc_id": "180724473",
        "date": "2013.09.17."
    },
    {
        "doc_id": "180726828",
        "date": "2013.09.17."
    },
    {
        "doc_id": "180719099",
        "date": "2013.09.17."
    },
    {
        "doc_id": "180296168",
        "date": "2013.09.10."
    },
    {
        "doc_id": "180296182",
        "date": "2013.09.10."
    },
    {
        "doc_id": "180021158",
        "date": "2013.09.06."
    },
    {
        "doc_id": "180020451",
        "date": "2013.09.06."
    },
    {
        "doc_id": "179682139",
        "date": "2013.09.06."
    },
    {
        "doc_id": "179860495",
        "date": "2013.09.03."
    },
    {
        "doc_id": "179867839",
        "date": "2013.09.03."
    },
    {
        "doc_id": "179800755",
        "date": "2013.09.02."
    },
    {
        "doc_id": "179807011",
        "date": "2013.09.02."
    },
    {
        "doc_id": "179804928",
        "date": "2013.09.02."
    },
    {
        "doc_id": "179764835",
        "date": "2013.09.02."
    },
    {
        "doc_id": "179148600",
        "date": "2013.08.23."
    },
    {
        "doc_id": "179162321",
        "date": "2013.08.23."
    },
    {
        "doc_id": "179106619",
        "date": "2013.08.22."
    },
    {
        "doc_id": "178842518",
        "date": "2013.08.18."
    },
    {
        "doc_id": "178779862",
        "date": "2013.08.17."
    },
    {
        "doc_id": "178755833",
        "date": "2013.08.17."
    },
    {
        "doc_id": "178726614",
        "date": "2013.08.16."
    },
    {
        "doc_id": "178561429",
        "date": "2013.08.16."
    },
    {
        "doc_id": "178704902",
        "date": "2013.08.16."
    },
    {
        "doc_id": "178698232",
        "date": "2013.08.16."
    },
    {
        "doc_id": "178715081",
        "date": "2013.08.16."
    },
    {
        "doc_id": "178718128",
        "date": "2013.08.16."
    },
    {
        "doc_id": "178710876",
        "date": "2013.08.16."
    },
    {
        "doc_id": "178638814",
        "date": "2013.08.16."
    },
    {
        "doc_id": "178329477",
        "date": "2013.08.16."
    },
    {
        "doc_id": "178708154",
        "date": "2013.08.16."
    },
    {
        "doc_id": "178553866",
        "date": "2013.08.16."
    },
    {
        "doc_id": "178061453",
        "date": "2013.08.07."
    },
    {
        "doc_id": "177714754",
        "date": "2013.08.05."
    },
    {
        "doc_id": "177673262",
        "date": "2013.08.05."
    },
    {
        "doc_id": "177945250",
        "date": "2013.08.05."
    },
    {
        "doc_id": "177916819",
        "date": "2013.08.05."
    },
    {
        "doc_id": "177944969",
        "date": "2013.08.05."
    },
    {
        "doc_id": "177944195",
        "date": "2013.08.05."
    },
    {
        "doc_id": "177930900",
        "date": "2013.08.05."
    },
    {
        "doc_id": "177943453",
        "date": "2013.08.05."
    },
    {
        "doc_id": "177487702",
        "date": "2013.08.05."
    },
    {
        "doc_id": "177915404",
        "date": "2013.08.05."
    },
    {
        "doc_id": "177934674",
        "date": "2013.08.05."
    },
    {
        "doc_id": "177848961",
        "date": "2013.08.05."
    },
    {
        "doc_id": "177936018",
        "date": "2013.08.05."
    },
    {
        "doc_id": "177936830",
        "date": "2013.08.05."
    },
    {
        "doc_id": "177936986",
        "date": "2013.08.05."
    },
    {
        "doc_id": "177907456",
        "date": "2013.08.05."
    },
    {
        "doc_id": "177909843",
        "date": "2013.08.05."
    },
    {
        "doc_id": "177939986",
        "date": "2013.08.05."
    },
    {
        "doc_id": "177933398",
        "date": "2013.08.05."
    },
    {
        "doc_id": "177927509",
        "date": "2013.08.05."
    },
    {
        "doc_id": "177687964",
        "date": "2013.08.02."
    },
    {
        "doc_id": "177636775",
        "date": "2013.07.31."
    },
    {
        "doc_id": "177423306",
        "date": "2013.07.28."
    },
    {
        "doc_id": "177387121",
        "date": "2013.07.28."
    },
    {
        "doc_id": "177422604",
        "date": "2013.07.28."
    },
    {
        "doc_id": "177397139",
        "date": "2013.07.27."
    },
    {
        "doc_id": "177382838",
        "date": "2013.07.27."
    },
    {
        "doc_id": "177272930",
        "date": "2013.07.27."
    },
    {
        "doc_id": "177140075",
        "date": "2013.07.24."
    },
    {
        "doc_id": "177067796",
        "date": "2013.07.23."
    },
    {
        "doc_id": "177081515",
        "date": "2013.07.23."
    },
    {
        "doc_id": "177079538",
        "date": "2013.07.23."
    },
    {
        "doc_id": "177030520",
        "date": "2013.07.22."
    },
    {
        "doc_id": "177018604",
        "date": "2013.07.22."
    },
    {
        "doc_id": "176984931",
        "date": "2013.07.22."
    },
    {
        "doc_id": "176907305",
        "date": "2013.07.22."
    },
    {
        "doc_id": "176895659",
        "date": "2013.07.20."
    },
    {
        "doc_id": "176908726",
        "date": "2013.07.20."
    },
    {
        "doc_id": "176902822",
        "date": "2013.07.20."
    },
    {
        "doc_id": "176900235",
        "date": "2013.07.20."
    },
    {
        "doc_id": "176756981",
        "date": "2013.07.20."
    },
    {
        "doc_id": "176829517",
        "date": "2013.07.20."
    },
    {
        "doc_id": "176882313",
        "date": "2013.07.20."
    },
    {
        "doc_id": "176878730",
        "date": "2013.07.20."
    },
    {
        "doc_id": "176897405",
        "date": "2013.07.20."
    },
    {
        "doc_id": "176897548",
        "date": "2013.07.20."
    },
    {
        "doc_id": "176670336",
        "date": "2013.07.17."
    },
    {
        "doc_id": "176711363",
        "date": "2013.07.17."
    },
    {
        "doc_id": "176714886",
        "date": "2013.07.17."
    },
    {
        "doc_id": "176705883",
        "date": "2013.07.17."
    },
    {
        "doc_id": "176706373",
        "date": "2013.07.17."
    },
    {
        "doc_id": "176697798",
        "date": "2013.07.17."
    },
    {
        "doc_id": "176711113",
        "date": "2013.07.17."
    },
    {
        "doc_id": "176655019",
        "date": "2013.07.16."
    },
    {
        "doc_id": "176633950",
        "date": "2013.07.16."
    },
    {
        "doc_id": "176640811",
        "date": "2013.07.16."
    },
    {
        "doc_id": "176586696",
        "date": "2013.07.15."
    },
    {
        "doc_id": "176551454",
        "date": "2013.07.15."
    },
    {
        "doc_id": "176583146",
        "date": "2013.07.15."
    },
    {
        "doc_id": "176516661",
        "date": "2013.07.15."
    },
    {
        "doc_id": "176518156",
        "date": "2013.07.15."
    },
    {
        "doc_id": "176556320",
        "date": "2013.07.15."
    },
    {
        "doc_id": "176564511",
        "date": "2013.07.15."
    },
    {
        "doc_id": "176567943",
        "date": "2013.07.15."
    },
    {
        "doc_id": "176581922",
        "date": "2013.07.15."
    },
    {
        "doc_id": "176580366",
        "date": "2013.07.15."
    },
    {
        "doc_id": "176205836",
        "date": "2013.07.09."
    },
    {
        "doc_id": "176153836",
        "date": "2013.07.08."
    },
    {
        "doc_id": "175908904",
        "date": "2013.07.08."
    },
    {
        "doc_id": "175883318",
        "date": "2013.07.08."
    },
    {
        "doc_id": "176037884",
        "date": "2013.07.08."
    },
    {
        "doc_id": "175959167",
        "date": "2013.07.08."
    },
    {
        "doc_id": "176151846",
        "date": "2013.07.08."
    },
    {
        "doc_id": "176143211",
        "date": "2013.07.08."
    },
    {
        "doc_id": "176077411",
        "date": "2013.07.08."
    },
    {
        "doc_id": "176098126",
        "date": "2013.07.08."
    },
    {
        "doc_id": "176142183",
        "date": "2013.07.08."
    },
    {
        "doc_id": "176121342",
        "date": "2013.07.08."
    },
    {
        "doc_id": "176051877",
        "date": "2013.07.08."
    },
    {
        "doc_id": "176138292",
        "date": "2013.07.08."
    },
    {
        "doc_id": "176122570",
        "date": "2013.07.08."
    },
    {
        "doc_id": "176140816",
        "date": "2013.07.08."
    },
    {
        "doc_id": "175954196",
        "date": "2013.07.08."
    },
    {
        "doc_id": "175820038",
        "date": "2013.07.05."
    },
    {
        "doc_id": "175814574",
        "date": "2013.07.03."
    },
    {
        "doc_id": "175766267",
        "date": "2013.07.02."
    },
    {
        "doc_id": "175757390",
        "date": "2013.07.02."
    },
    {
        "doc_id": "175757699",
        "date": "2013.07.02."
    },
    {
        "doc_id": "175756946",
        "date": "2013.07.02."
    },
    {
        "doc_id": "175742705",
        "date": "2013.07.02."
    },
    {
        "doc_id": "175756860",
        "date": "2013.07.02."
    },
    {
        "doc_id": "175375758",
        "date": "2013.07.01."
    },
    {
        "doc_id": "175493196",
        "date": "2013.07.01."
    },
    {
        "doc_id": "175704515",
        "date": "2013.07.01."
    },
    {
        "doc_id": "175542323",
        "date": "2013.07.01."
    },
    {
        "doc_id": "175598853",
        "date": "2013.07.01."
    },
    {
        "doc_id": "175617434",
        "date": "2013.07.01."
    },
    {
        "doc_id": "175668299",
        "date": "2013.07.01."
    },
    {
        "doc_id": "175697860",
        "date": "2013.07.01."
    },
    {
        "doc_id": "175611144",
        "date": "2013.07.01."
    },
    {
        "doc_id": "175674060",
        "date": "2013.07.01."
    },
    {
        "doc_id": "175333624",
        "date": "2013.07.01."
    },
    {
        "doc_id": "175691883",
        "date": "2013.07.01."
    },
    {
        "doc_id": "175086801",
        "date": "2013.06.21."
    },
    {
        "doc_id": "175073458",
        "date": "2013.06.21."
    },
    {
        "doc_id": "175074000",
        "date": "2013.06.21."
    },
    {
        "doc_id": "175059056",
        "date": "2013.06.21."
    },
    {
        "doc_id": "175042896",
        "date": "2013.06.21."
    },
    {
        "doc_id": "175072265",
        "date": "2013.06.21."
    },
    {
        "doc_id": "174972227",
        "date": "2013.06.20."
    },
    {
        "doc_id": "174991994",
        "date": "2013.06.20."
    },
    {
        "doc_id": "175019980",
        "date": "2013.06.20."
    },
    {
        "doc_id": "174950838",
        "date": "2013.06.20."
    },
    {
        "doc_id": "175020189",
        "date": "2013.06.20."
    },
    {
        "doc_id": "175019267",
        "date": "2013.06.20."
    },
    {
        "doc_id": "174665703",
        "date": "2013.06.20."
    },
    {
        "doc_id": "175021966",
        "date": "2013.06.20."
    },
    {
        "doc_id": "175006585",
        "date": "2013.06.20."
    },
    {
        "doc_id": "175002445",
        "date": "2013.06.20."
    },
    {
        "doc_id": "175009729",
        "date": "2013.06.20."
    },
    {
        "doc_id": "174905721",
        "date": "2013.06.18."
    },
    {
        "doc_id": "174846174",
        "date": "2013.06.18."
    },
    {
        "doc_id": "174758023",
        "date": "2013.06.17."
    },
    {
        "doc_id": "174789048",
        "date": "2013.06.17."
    },
    {
        "doc_id": "174818665",
        "date": "2013.06.17."
    },
    {
        "doc_id": "174690122",
        "date": "2013.06.15."
    },
    {
        "doc_id": "174646494",
        "date": "2013.06.14."
    },
    {
        "doc_id": "174647321",
        "date": "2013.06.14."
    },
    {
        "doc_id": "174646526",
        "date": "2013.06.14."
    },
    {
        "doc_id": "174648594",
        "date": "2013.06.14."
    },
    {
        "doc_id": "174646188",
        "date": "2013.06.14."
    },
    {
        "doc_id": "174576587",
        "date": "2013.06.14."
    },
    {
        "doc_id": "174640597",
        "date": "2013.06.14."
    },
    {
        "doc_id": "174638784",
        "date": "2013.06.14."
    },
    {
        "doc_id": "174596305",
        "date": "2013.06.14."
    },
    {
        "doc_id": "174623469",
        "date": "2013.06.14."
    },
    {
        "doc_id": "174623806",
        "date": "2013.06.14."
    },
    {
        "doc_id": "174603430",
        "date": "2013.06.14."
    },
    {
        "doc_id": "174559763",
        "date": "2013.06.13."
    },
    {
        "doc_id": "174576393",
        "date": "2013.06.13."
    },
    {
        "doc_id": "174578040",
        "date": "2013.06.13."
    },
    {
        "doc_id": "174520808",
        "date": "2013.06.12."
    },
    {
        "doc_id": "174518015",
        "date": "2013.06.12."
    },
    {
        "doc_id": "174504877",
        "date": "2013.06.12."
    },
    {
        "doc_id": "174449577",
        "date": "2013.06.12."
    },
    {
        "doc_id": "174488240",
        "date": "2013.06.12."
    },
    {
        "doc_id": "174499499",
        "date": "2013.06.12."
    },
    {
        "doc_id": "174509664",
        "date": "2013.06.12."
    },
    {
        "doc_id": "174509821",
        "date": "2013.06.12."
    },
    {
        "doc_id": "174446894",
        "date": "2013.06.11."
    },
    {
        "doc_id": "174276885",
        "date": "2013.06.11."
    },
    {
        "doc_id": "174205985",
        "date": "2013.06.11."
    },
    {
        "doc_id": "174437105",
        "date": "2013.06.11."
    },
    {
        "doc_id": "174407253",
        "date": "2013.06.11."
    },
    {
        "doc_id": "174066885",
        "date": "2013.06.11."
    },
    {
        "doc_id": "174441723",
        "date": "2013.06.11."
    },
    {
        "doc_id": "174437909",
        "date": "2013.06.11."
    },
    {
        "doc_id": "174443529",
        "date": "2013.06.11."
    },
    {
        "doc_id": "174179191",
        "date": "2013.06.10."
    },
    {
        "doc_id": "174322753",
        "date": "2013.06.10."
    },
    {
        "doc_id": "174328022",
        "date": "2013.06.10."
    },
    {
        "doc_id": "174334564",
        "date": "2013.06.10."
    },
    {
        "doc_id": "174359291",
        "date": "2013.06.10."
    },
    {
        "doc_id": "174361019",
        "date": "2013.06.10."
    },
    {
        "doc_id": "174378348",
        "date": "2013.06.10."
    },
    {
        "doc_id": "174090252",
        "date": "2013.06.07."
    },
    {
        "doc_id": "174029471",
        "date": "2013.06.07."
    },
    {
        "doc_id": "174153115",
        "date": "2013.06.07."
    },
    {
        "doc_id": "174045224",
        "date": "2013.06.07."
    },
    {
        "doc_id": "174083203",
        "date": "2013.06.06."
    },
    {
        "doc_id": "174096347",
        "date": "2013.06.06."
    },
    {
        "doc_id": "174099785",
        "date": "2013.06.06."
    },
    {
        "doc_id": "174109165",
        "date": "2013.06.06."
    },
    {
        "doc_id": "173974660",
        "date": "2013.06.05."
    },
    {
        "doc_id": "173975758",
        "date": "2013.06.05."
    }
]