[
    {
        "doc_id": "315395721",
        "date": "2018.11.29."
    },
    {
        "doc_id": "315004335",
        "date": "2018.11.25."
    },
    {
        "doc_id": "314999107",
        "date": "2018.11.25."
    },
    {
        "doc_id": "314993779",
        "date": "2018.11.23."
    },
    {
        "doc_id": "315020806",
        "date": "2018.11.23."
    },
    {
        "doc_id": "315027312",
        "date": "2018.11.23."
    },
    {
        "doc_id": "315038915",
        "date": "2018.11.23."
    },
    {
        "doc_id": "315040106",
        "date": "2018.11.23."
    },
    {
        "doc_id": "314889281",
        "date": "2018.11.22."
    },
    {
        "doc_id": "314930775",
        "date": "2018.11.22."
    },
    {
        "doc_id": "314943214",
        "date": "2018.11.22."
    },
    {
        "doc_id": "314963527",
        "date": "2018.11.22."
    },
    {
        "doc_id": "314697038",
        "date": "2018.11.20."
    },
    {
        "doc_id": "314737707",
        "date": "2018.11.20."
    },
    {
        "doc_id": "314802810",
        "date": "2018.11.20."
    },
    {
        "doc_id": "314805759",
        "date": "2018.11.20."
    },
    {
        "doc_id": "314806090",
        "date": "2018.11.20."
    },
    {
        "doc_id": "314347121",
        "date": "2018.11.14."
    },
    {
        "doc_id": "314117945",
        "date": "2018.11.14."
    },
    {
        "doc_id": "314271765",
        "date": "2018.11.13."
    },
    {
        "doc_id": "313927264",
        "date": "2018.11.08."
    },
    {
        "doc_id": "313849203",
        "date": "2018.11.08."
    },
    {
        "doc_id": "313841941",
        "date": "2018.11.08."
    },
    {
        "doc_id": "313923395",
        "date": "2018.11.08."
    },
    {
        "doc_id": "313857621",
        "date": "2018.11.08."
    },
    {
        "doc_id": "313858964",
        "date": "2018.11.08."
    },
    {
        "doc_id": "313389743",
        "date": "2018.11.04."
    },
    {
        "doc_id": "313422799",
        "date": "2018.11.04."
    },
    {
        "doc_id": "313441764",
        "date": "2018.11.04."
    },
    {
        "doc_id": "313510732",
        "date": "2018.11.04."
    },
    {
        "doc_id": "313465431",
        "date": "2018.11.02."
    },
    {
        "doc_id": "310808598",
        "date": "2018.09.30."
    },
    {
        "doc_id": "310799235",
        "date": "2018.09.30."
    },
    {
        "doc_id": "310820576",
        "date": "2018.09.30."
    },
    {
        "doc_id": "310835006",
        "date": "2018.09.30."
    },
    {
        "doc_id": "310863638",
        "date": "2018.09.30."
    },
    {
        "doc_id": "310553608",
        "date": "2018.09.29."
    },
    {
        "doc_id": "310660649",
        "date": "2018.09.29."
    },
    {
        "doc_id": "310721771",
        "date": "2018.09.29."
    },
    {
        "doc_id": "310814161",
        "date": "2018.09.29."
    },
    {
        "doc_id": "310862908",
        "date": "2018.09.29."
    },
    {
        "doc_id": "310873620",
        "date": "2018.09.29."
    },
    {
        "doc_id": "310491677",
        "date": "2018.09.29."
    },
    {
        "doc_id": "309595893",
        "date": "2018.09.14."
    },
    {
        "doc_id": "309558130",
        "date": "2018.09.14."
    },
    {
        "doc_id": "309596071",
        "date": "2018.09.14."
    },
    {
        "doc_id": "309607807",
        "date": "2018.09.14."
    },
    {
        "doc_id": "309619439",
        "date": "2018.09.14."
    },
    {
        "doc_id": "309698344",
        "date": "2018.09.14."
    },
    {
        "doc_id": "309768820",
        "date": "2018.09.14."
    },
    {
        "doc_id": "309806193",
        "date": "2018.09.14."
    },
    {
        "doc_id": "309848802",
        "date": "2018.09.14."
    },
    {
        "doc_id": "309859436",
        "date": "2018.09.14."
    },
    {
        "doc_id": "309866462",
        "date": "2018.09.14."
    },
    {
        "doc_id": "309913064",
        "date": "2018.09.13."
    },
    {
        "doc_id": "305448077",
        "date": "2018.07.14."
    },
    {
        "doc_id": "302854607",
        "date": "2018.06.12."
    },
    {
        "doc_id": "297730745",
        "date": "2018.03.29."
    },
    {
        "doc_id": "297982838",
        "date": "2018.03.29."
    },
    {
        "doc_id": "297548230",
        "date": "2018.03.20."
    },
    {
        "doc_id": "295337990",
        "date": "2018.02.23."
    },
    {
        "doc_id": "295148943",
        "date": "2018.02.21."
    },
    {
        "doc_id": "294772174",
        "date": "2018.02.14."
    },
    {
        "doc_id": "294850367",
        "date": "2018.02.13."
    },
    {
        "doc_id": "294239316",
        "date": "2018.02.09."
    },
    {
        "doc_id": "293270347",
        "date": "2018.01.27."
    },
    {
        "doc_id": "293192187",
        "date": "2018.01.26."
    },
    {
        "doc_id": "293096127",
        "date": "2018.01.25."
    },
    {
        "doc_id": "293143864",
        "date": "2018.01.24."
    },
    {
        "doc_id": "292949819",
        "date": "2018.01.24."
    },
    {
        "doc_id": "292505844",
        "date": "2018.01.24."
    },
    {
        "doc_id": "292432196",
        "date": "2018.01.17."
    },
    {
        "doc_id": "292265288",
        "date": "2018.01.17."
    },
    {
        "doc_id": "292439329",
        "date": "2018.01.17."
    },
    {
        "doc_id": "292507849",
        "date": "2018.01.17."
    },
    {
        "doc_id": "292510632",
        "date": "2018.01.17."
    },
    {
        "doc_id": "292030166",
        "date": "2018.01.10."
    },
    {
        "doc_id": "292110044",
        "date": "2018.01.10."
    },
    {
        "doc_id": "291560444",
        "date": "2018.01.10."
    },
    {
        "doc_id": "291555139",
        "date": "2018.01.10."
    },
    {
        "doc_id": "291866919",
        "date": "2018.01.10."
    },
    {
        "doc_id": "291650157",
        "date": "2018.01.10."
    },
    {
        "doc_id": "291576187",
        "date": "2018.01.10."
    },
    {
        "doc_id": "291569447",
        "date": "2018.01.10."
    },
    {
        "doc_id": "291609390",
        "date": "2018.01.10."
    },
    {
        "doc_id": "291506830",
        "date": "2018.01.10."
    },
    {
        "doc_id": "291512692",
        "date": "2018.01.04."
    },
    {
        "doc_id": "291020107",
        "date": "2017.12.30."
    },
    {
        "doc_id": "290974219",
        "date": "2017.12.30."
    },
    {
        "doc_id": "290933053",
        "date": "2017.12.30."
    },
    {
        "doc_id": "290809054",
        "date": "2017.12.30."
    },
    {
        "doc_id": "290727617",
        "date": "2017.12.30."
    },
    {
        "doc_id": "290718670",
        "date": "2017.12.30."
    },
    {
        "doc_id": "291054438",
        "date": "2017.12.30."
    },
    {
        "doc_id": "291095245",
        "date": "2017.12.30."
    },
    {
        "doc_id": "290718110",
        "date": "2017.12.30."
    },
    {
        "doc_id": "290698943",
        "date": "2017.12.30."
    },
    {
        "doc_id": "290790453",
        "date": "2017.12.30."
    },
    {
        "doc_id": "291057188",
        "date": "2017.12.30."
    },
    {
        "doc_id": "291057127",
        "date": "2017.12.30."
    },
    {
        "doc_id": "291053664",
        "date": "2017.12.30."
    },
    {
        "doc_id": "290777404",
        "date": "2017.12.26."
    },
    {
        "doc_id": "290780461",
        "date": "2017.12.25."
    },
    {
        "doc_id": "290771984",
        "date": "2017.12.25."
    },
    {
        "doc_id": "290697296",
        "date": "2017.12.25."
    },
    {
        "doc_id": "290796453",
        "date": "2017.12.25."
    },
    {
        "doc_id": "290691726",
        "date": "2017.12.25."
    },
    {
        "doc_id": "290614217",
        "date": "2017.12.24."
    },
    {
        "doc_id": "290689377",
        "date": "2017.12.24."
    },
    {
        "doc_id": "290623188",
        "date": "2017.12.24."
    },
    {
        "doc_id": "290623015",
        "date": "2017.12.24."
    },
    {
        "doc_id": "290623709",
        "date": "2017.12.24."
    },
    {
        "doc_id": "290724738",
        "date": "2017.12.24."
    },
    {
        "doc_id": "290614127",
        "date": "2017.12.24."
    },
    {
        "doc_id": "290614356",
        "date": "2017.12.24."
    },
    {
        "doc_id": "290623383",
        "date": "2017.12.24."
    },
    {
        "doc_id": "290623633",
        "date": "2017.12.24."
    },
    {
        "doc_id": "290695259",
        "date": "2017.12.24."
    },
    {
        "doc_id": "290820898",
        "date": "2017.12.24."
    },
    {
        "doc_id": "290821150",
        "date": "2017.12.24."
    },
    {
        "doc_id": "290822273",
        "date": "2017.12.24."
    },
    {
        "doc_id": "290818872",
        "date": "2017.12.23."
    },
    {
        "doc_id": "290821461",
        "date": "2017.12.23."
    },
    {
        "doc_id": "290822796",
        "date": "2017.12.23."
    },
    {
        "doc_id": "290443789",
        "date": "2017.12.21."
    },
    {
        "doc_id": "290487461",
        "date": "2017.12.21."
    },
    {
        "doc_id": "290689177",
        "date": "2017.12.21."
    },
    {
        "doc_id": "290488712",
        "date": "2017.12.18."
    },
    {
        "doc_id": "289984270",
        "date": "2017.12.15."
    },
    {
        "doc_id": "290293755",
        "date": "2017.12.15."
    },
    {
        "doc_id": "290287531",
        "date": "2017.12.14."
    },
    {
        "doc_id": "290271438",
        "date": "2017.12.14."
    },
    {
        "doc_id": "290300191",
        "date": "2017.12.14."
    },
    {
        "doc_id": "290062384",
        "date": "2017.12.13."
    },
    {
        "doc_id": "290017718",
        "date": "2017.12.13."
    },
    {
        "doc_id": "289991949",
        "date": "2017.12.13."
    },
    {
        "doc_id": "289805319",
        "date": "2017.12.13."
    },
    {
        "doc_id": "289795390",
        "date": "2017.12.13."
    },
    {
        "doc_id": "290103477",
        "date": "2017.12.12."
    },
    {
        "doc_id": "290091519",
        "date": "2017.12.12."
    },
    {
        "doc_id": "290064346",
        "date": "2017.12.12."
    },
    {
        "doc_id": "290029639",
        "date": "2017.12.12."
    },
    {
        "doc_id": "290113623",
        "date": "2017.12.12."
    },
    {
        "doc_id": "289879454",
        "date": "2017.12.12."
    },
    {
        "doc_id": "289609806",
        "date": "2017.12.08."
    },
    {
        "doc_id": "289873567",
        "date": "2017.12.08."
    },
    {
        "doc_id": "289652763",
        "date": "2017.12.08."
    },
    {
        "doc_id": "289366891",
        "date": "2017.12.07."
    },
    {
        "doc_id": "289590199",
        "date": "2017.12.07."
    },
    {
        "doc_id": "289739110",
        "date": "2017.12.06."
    },
    {
        "doc_id": "289617332",
        "date": "2017.12.06."
    },
    {
        "doc_id": "289455483",
        "date": "2017.12.05."
    },
    {
        "doc_id": "289372937",
        "date": "2017.12.05."
    },
    {
        "doc_id": "289465649",
        "date": "2017.12.05."
    },
    {
        "doc_id": "289633226",
        "date": "2017.12.05."
    },
    {
        "doc_id": "289407999",
        "date": "2017.12.02."
    },
    {
        "doc_id": "289407714",
        "date": "2017.12.02."
    },
    {
        "doc_id": "289372086",
        "date": "2017.12.02."
    },
    {
        "doc_id": "289010309",
        "date": "2017.11.26."
    },
    {
        "doc_id": "289042767",
        "date": "2017.11.26."
    },
    {
        "doc_id": "289014979",
        "date": "2017.11.26."
    },
    {
        "doc_id": "289014738",
        "date": "2017.11.26."
    },
    {
        "doc_id": "289013963",
        "date": "2017.11.26."
    },
    {
        "doc_id": "289013616",
        "date": "2017.11.26."
    },
    {
        "doc_id": "289009560",
        "date": "2017.11.26."
    },
    {
        "doc_id": "289007491",
        "date": "2017.11.26."
    },
    {
        "doc_id": "288957348",
        "date": "2017.11.26."
    },
    {
        "doc_id": "288856909",
        "date": "2017.11.26."
    },
    {
        "doc_id": "288848627",
        "date": "2017.11.26."
    },
    {
        "doc_id": "288603539",
        "date": "2017.11.19."
    },
    {
        "doc_id": "288586021",
        "date": "2017.11.18."
    },
    {
        "doc_id": "288570994",
        "date": "2017.11.18."
    },
    {
        "doc_id": "288534463",
        "date": "2017.11.17."
    },
    {
        "doc_id": "288378677",
        "date": "2017.11.17."
    },
    {
        "doc_id": "288460652",
        "date": "2017.11.17."
    },
    {
        "doc_id": "288324636",
        "date": "2017.11.17."
    },
    {
        "doc_id": "288347007",
        "date": "2017.11.17."
    },
    {
        "doc_id": "288544631",
        "date": "2017.11.17."
    },
    {
        "doc_id": "288228840",
        "date": "2017.11.13."
    },
    {
        "doc_id": "288268489",
        "date": "2017.11.13."
    },
    {
        "doc_id": "288074673",
        "date": "2017.11.12."
    },
    {
        "doc_id": "288088669",
        "date": "2017.11.12."
    },
    {
        "doc_id": "288118807",
        "date": "2017.11.12."
    },
    {
        "doc_id": "288124242",
        "date": "2017.11.12."
    },
    {
        "doc_id": "287992229",
        "date": "2017.11.11."
    },
    {
        "doc_id": "287992490",
        "date": "2017.11.09."
    },
    {
        "doc_id": "287944337",
        "date": "2017.11.09."
    },
    {
        "doc_id": "288034399",
        "date": "2017.11.09."
    },
    {
        "doc_id": "287927681",
        "date": "2017.11.07."
    },
    {
        "doc_id": "287921858",
        "date": "2017.11.07."
    },
    {
        "doc_id": "287852778",
        "date": "2017.11.06."
    },
    {
        "doc_id": "287877441",
        "date": "2017.11.06."
    }
]